{"ad_search_list":null,"banner_dark":{"uri":"32e5200049fac86168117","url_list":["https://p3-sign.douyinpic.com/obj/32e5200049fac86168117?x-expires=1660759200&x-signature=SW5PI9uGw33b3G6NMSu0BIl0JBs%3D&from=65706370"]},"banner_light":{"uri":"321f4000f703369c24604","url_list":["https://p3-sign.douyinpic.com/obj/321f4000f703369c24604?x-expires=1660759200&x-signature=BgDN2ekm4%2FgcTPvPzAq%2F1fyfJU8%3D&from=65706370"]},"board_tabs":null,"extra":{"now":1660740860000,"fatal_item_ids":[],"logid":"20220817205420010208143229231FF8E2"},"log_pb":{"impr_id":"20220817205420010208143229231FF8E2"},"status_code":0,"data":{"word_list":[{"room_count":0,"discuss_video_count":1,"word_sub_board":null,"article_detail_count":0,"word":"接英雄万惠文回家","hot_value":10478890,"video_count":8,"word_type":1,"related_words":null,"drift_info":null,"label":3,"word_cover":{"uri":"tos-cn-p-0015/37c3b79afba342e29073bb8f211d34c9","url_list":["https://p3-sign.douyinpic.com/tos-cn-p-0015/37c3b79afba342e29073bb8f211d34c9~noop.jpeg?x-expires=1660759200&x-signature=a%2B6fTSnoUgc%2FPbev%2BxAmODI6ubk%3D&from=3218412987","https://p26-sign.douyinpic.com/tos-cn-p-0015/37c3b79afba342e29073bb8f211d34c9~noop.jpeg?x-expires=1660759200&x-signature=45Ld%2FVog8m2sM8kFomGBhl7uvLk%3D&from=3218412987","https://p6-sign.douyinpic.com/tos-cn-p-0015/37c3b79afba342e29073bb8f211d34c9~noop.jpeg?x-expires=1660759200&x-signature=Hyj%2FR5sNCRc%2Fw4SMhOGMOvp2SkA%3D&from=3218412987"]},"sentence_id":"772449","event_time":1660698936,"view_count":71486941,"hotlist_param":"{\"version\":1}","aweme_infos":null,"challenge_id":"","group_id":"7131638584407364898","can_extend_detail":false,"sentence_tag":4003,"position":1},{"position":2,"hotlist_param":"{\"version\":1}","discuss_video_count":1,"article_detail_count":1,"label":3,"hot_value":10417492,"challenge_id":"","video_count":2,"drift_info":null,"word_cover":{"uri":"tos-cn-p-0015/8dc1b25f87e345438f32f9fcb34d1170_1660635737","url_list":["https://p26-sign.douyinpic.com/tos-cn-p-0015/8dc1b25f87e345438f32f9fcb34d1170_1660635737~noop.jpeg?x-expires=1660759200&x-signature=dIev5L74UEuDGKFumvpEP%2FOpIWU%3D&from=3218412987","https://p9-sign.douyinpic.com/tos-cn-p-0015/8dc1b25f87e345438f32f9fcb34d1170_1660635737~noop.jpeg?x-expires=1660759200&x-signature=t4OiQSXQlw6HrBQvzPg%2BMztr4a0%3D&from=3218412987","https://p3-sign.douyinpic.com/tos-cn-p-0015/8dc1b25f87e345438f32f9fcb34d1170_1660635737~noop.jpeg?x-expires=1660759200&x-signature=L4fMnEU%2BKOQaCgrQo5nuxMEwkbI%3D&from=3218412987"]},"sentence_id":"771803","aweme_infos":null,"word_sub_board":null,"view_count":63906178,"sentence_tag":4004,"word":"95后小伙上班2年胖100斤","group_id":"7131905301418710279","word_type":1,"event_time":1660642589,"related_words":null},{"aweme_infos":null,"discuss_video_count":1,"word_sub_board":null,"challenge_id":"","sentence_id":"772439","event_time":1660698416,"word":"95后飞行员在校就飞歼10","word_cover":{"uri":"tos-cn-p-0015/0f72e7656aef4fda904e160a307838a0_1660641566","url_list":["https://p3-sign.douyinpic.com/tos-cn-p-0015/0f72e7656aef4fda904e160a307838a0_1660641566~noop.jpeg?x-expires=1660759200&x-signature=ZxeHashNWjCzp5XJS5v2oSDyEbc%3D&from=3218412987","https://p26-sign.douyinpic.com/tos-cn-p-0015/0f72e7656aef4fda904e160a307838a0_1660641566~noop.jpeg?x-expires=1660759200&x-signature=gnVU4o2%2Fg7%2FccpQhcWum%2F3525do%3D&from=3218412987","https://p6-sign.douyinpic.com/tos-cn-p-0015/0f72e7656aef4fda904e160a307838a0_1660641566~noop.jpeg?x-expires=1660759200&x-signature=dIfrZB8yMWM01Dd5ONOe9vzx4Rc%3D&from=3218412987"]},"video_count":3,"related_words":null,"hot_value":10285217,"position":3,"group_id":"7132383054652658948","drift_info":null,"hotlist_param":"{\"version\":1}","sentence_tag":21000,"article_detail_count":0,"label":4,"word_type":1,"view_count":62880006},{"drift_info":null,"discuss_video_count":1,"article_detail_count":0,"related_words":null,"hotlist_param":"{\"version\":1}","challenge_id":"","video_count":5,"word_type":1,"group_id":"7132385244607288588","sentence_id":"772947","event_time":1660717160,"view_count":60540672,"aweme_infos":null,"word":"比亚迪汉被曝上牌3天自燃","hot_value":10098231,"position":4,"sentence_tag":4004,"word_sub_board":null,"label":3,"word_cover":{"url_list":["https://p26-sign.douyinpic.com/tos-cn-p-0015/e3ef1738748944ecaa8c4e3bba939628~noop.jpeg?x-expires=1660759200&x-signature=Qy1r8%2BFV3%2BesE6oSLD1TrlYq6hU%3D&from=3218412987","https://p9-sign.douyinpic.com/tos-cn-p-0015/e3ef1738748944ecaa8c4e3bba939628~noop.jpeg?x-expires=1660759200&x-signature=5yzM9623XKAraOYuPddQ5bzUIJs%3D&from=3218412987","https://p3-sign.douyinpic.com/tos-cn-p-0015/e3ef1738748944ecaa8c4e3bba939628~noop.jpeg?x-expires=1660759200&x-signature=BO8KilWbCyOLNNzEPGauNtdKjXU%3D&from=3218412987"],"uri":"tos-cn-p-0015/e3ef1738748944ecaa8c4e3bba939628"}},{"position":5,"group_id":"7131688847470122273","word_type":1,"sentence_id":"773318","related_words":null,"word_sub_board":null,"hot_value":10074535,"challenge_id":"","view_count":61484452,"hotlist_param":"{\"version\":1}","aweme_infos":null,"video_count":5,"can_extend_detail":false,"discuss_video_count":1,"article_detail_count":0,"word":"央六点评明日战记","label":0,"word_cover":{"url_list":["https://p3-sign.douyinpic.com/tos-cn-p-0015/7bea724380864495aa63733054feb31b~noop.jpeg?x-expires=1660759200&x-signature=0KB0u1usgqM6JuRHV2IiB0ufbPY%3D&from=3218412987","https://p26-sign.douyinpic.com/tos-cn-p-0015/7bea724380864495aa63733054feb31b~noop.jpeg?x-expires=1660759200&x-signature=aeGslErLnCnyizttU48NBDBGWyI%3D&from=3218412987","https://p9-sign.douyinpic.com/tos-cn-p-0015/7bea724380864495aa63733054feb31b~noop.jpeg?x-expires=1660759200&x-signature=Of%2FrgJhEaoS8nfIhScEcbY08ABQ%3D&from=3218412987"],"uri":"tos-cn-p-0015/7bea724380864495aa63733054feb31b"},"event_time":1660728968,"drift_info":null,"sentence_tag":2001},{"discuss_video_count":1,"article_detail_count":0,"challenge_id":"","related_words":null,"view_count":56737436,"drift_info":null,"sentence_tag":6000,"word_sub_board":null,"word":"抖音联手百家媒体辟谣319万条","hot_value":9932760,"video_count":45,"group_id":"7131181641359562019","hotlist_param":"{\"version\":1}","label":3,"position":6,"display_style":0,"word_cover":{"uri":"tos-cn-p-0015/56208a2297d14e7aac9cab3a0935317d","url_list":["https://p3-sign.douyinpic.com/tos-cn-p-0015/56208a2297d14e7aac9cab3a0935317d~noop.jpeg?x-expires=1660759200&x-signature=3J4YkK3D33eNXwTP%2FCvl6tLVUfo%3D&from=3218412987","https://p6-sign.douyinpic.com/tos-cn-p-0015/56208a2297d14e7aac9cab3a0935317d~noop.jpeg?x-expires=1660759200&x-signature=d0irFCCKG%2Bp7A8pdIFEXcCaljA8%3D&from=3218412987","https://p9-sign.douyinpic.com/tos-cn-p-0015/56208a2297d14e7aac9cab3a0935317d~noop.jpeg?x-expires=1660759200&x-signature=Alm58kPRy3bbBZdyqT4BCWi6Y4w%3D&from=3218412987"]},"word_type":1,"sentence_id":"771804","event_time":1660642599,"aweme_infos":null},{"label":0,"event_time":1660725219,"view_count":61524219,"aweme_infos":null,"emo_label":0,"word":"苍兰诀王鹤棣扫楼生图","hot_value":9886251,"word_cover":{"uri":"tos-cn-p-0015/b382ff2ccb5c495e9f95deed8c3b7ee8_1660723104","url_list":["https://p6-sign.douyinpic.com/tos-cn-p-0015/b382ff2ccb5c495e9f95deed8c3b7ee8_1660723104~noop.jpeg?x-expires=1660759200&x-signature=Qr0yyoEvV3cWDfDxopmq0BPX%2FxM%3D&from=3218412987","https://p9-sign.douyinpic.com/tos-cn-p-0015/b382ff2ccb5c495e9f95deed8c3b7ee8_1660723104~noop.jpeg?x-expires=1660759200&x-signature=1yu5yrDPNdNqvQUAeAQphPsdPE4%3D&from=3218412987","https://p3-sign.douyinpic.com/tos-cn-p-0015/b382ff2ccb5c495e9f95deed8c3b7ee8_1660723104~noop.jpeg?x-expires=1660759200&x-signature=9MU8%2BnpUcl6dKG5QbI18eJ2B61w%3D&from=3218412987"]},"position":7,"video_count":2,"hotlist_param":"{\"version\":1}","challenge_id":"","group_id":"7132484759476884744","can_extend_detail":false,"word_type":1,"drift_info":null,"article_detail_count":0,"sentence_id":"773171","related_words":null,"sentence_tag":2002,"discuss_video_count":1,"word_sub_board":null},{"word_cover":{"uri":"tos-cn-p-0015/641e76cb193c40c394e654ad2e7c410a_1660714833","url_list":["https://p3-sign.douyinpic.com/tos-cn-p-0015/641e76cb193c40c394e654ad2e7c410a_1660714833~noop.jpeg?x-expires=1660759200&x-signature=MJkR%2BIzxTofFScdWB%2Flyav3nG40%3D&from=3218412987","https://p26-sign.douyinpic.com/tos-cn-p-0015/641e76cb193c40c394e654ad2e7c410a_1660714833~noop.jpeg?x-expires=1660759200&x-signature=gZPJxLnTQfdUQN6McptMiWJSX8o%3D&from=3218412987","https://p9-sign.douyinpic.com/tos-cn-p-0015/641e76cb193c40c394e654ad2e7c410a_1660714833~noop.jpeg?x-expires=1660759200&x-signature=Kf2Oc6MLetevHRnIMUVlth1VeMA%3D&from=3218412987"]},"word_type":1,"sentence_id":"772804","related_words":null,"sentence_tag":2002,"hot_value":9740790,"can_extend_detail":false,"view_count":62376890,"drift_info":null,"word_sub_board":null,"word":"偷偷藏不住路透照","challenge_id":"","position":8,"video_count":5,"group_id":"7131669306693555470","event_time":1660712857,"hotlist_param":"{\"version\":1}","article_detail_count":0,"label":3,"emo_label":0,"discuss_video_count":1,"aweme_infos":null},{"event_time":1660699901,"sentence_tag":4003,"word_type":1,"article_detail_count":0,"word":"女子商场试戒指戴上就跑","position":9,"view_count":57035618,"hotlist_param":"{\"version\":1}","word_sub_board":null,"video_count":1,"group_id":"7131695543060010243","challenge_id":"","word_cover":{"uri":"tos-cn-p-0015/4cac31d49fc847b795c4baad95dab8c8","url_list":["https://p9-sign.douyinpic.com/tos-cn-p-0015/4cac31d49fc847b795c4baad95dab8c8~noop.jpeg?x-expires=1660759200&x-signature=fFhTrlx5vM2TY8cUoNQ%2FBxp4LYw%3D&from=3218412987","https://p6-sign.douyinpic.com/tos-cn-p-0015/4cac31d49fc847b795c4baad95dab8c8~noop.jpeg?x-expires=1660759200&x-signature=AN72kMeTkNfNU2q5a7cOloHuPto%3D&from=3218412987","https://p3-sign.douyinpic.com/tos-cn-p-0015/4cac31d49fc847b795c4baad95dab8c8~noop.jpeg?x-expires=1660759200&x-signature=JBY5Q74eBQxA1FX1YJNAtzHyi98%3D&from=3218412987"]},"sentence_id":"772486","related_words":null,"drift_info":null,"aweme_infos":null,"label":3,"hot_value":9523049,"discuss_video_count":1},{"sentence_tag":21000,"discuss_video_count":1,"word":"解放军赴俄参加东方2022军演","hot_value":9490163,"challenge_id":"","position":10,"aweme_infos":null,"article_detail_count":0,"word_cover":{"uri":"tos-cn-p-0015/03ed45165be34d939301d899e06497d3","url_list":["https://p26-sign.douyinpic.com/tos-cn-p-0015/03ed45165be34d939301d899e06497d3~noop.jpeg?x-expires=1660759200&x-signature=A7FjwgAubhFeH5SpgLb8ymFCL5M%3D&from=3218412987","https://p9-sign.douyinpic.com/tos-cn-p-0015/03ed45165be34d939301d899e06497d3~noop.jpeg?x-expires=1660759200&x-signature=sy2RD%2FTXVvYIWsEgoEc%2FfX%2Bq%2FPI%3D&from=3218412987","https://p3-sign.douyinpic.com/tos-cn-p-0015/03ed45165be34d939301d899e06497d3~noop.jpeg?x-expires=1660759200&x-signature=6Ggs%2BLmpXWFD2OSzX2A5mPgMN24%3D&from=3218412987"]},"video_count":3,"group_id":"7131916334204343559","sentence_id":"773465","related_words":null,"label":1,"word_sub_board":null,"word_type":1,"event_time":1660732758,"view_count":56731377,"drift_info":null,"hotlist_param":"{\"version\":1}"},{"label":3,"challenge_id":"","video_count":5,"drift_info":null,"word_sub_board":null,"word_cover":{"uri":"tos-cn-p-0015/33daffcff1e840799f8b5353159fd1dd_1660704795","url_list":["https://p3-sign.douyinpic.com/tos-cn-p-0015/33daffcff1e840799f8b5353159fd1dd_1660704795~noop.jpeg?x-expires=1660759200&x-signature=nPRAGi5KUHrgZTIR5IwdYghFV%2Fo%3D&from=3218412987","https://p9-sign.douyinpic.com/tos-cn-p-0015/33daffcff1e840799f8b5353159fd1dd_1660704795~noop.jpeg?x-expires=1660759200&x-signature=opaenyCFsjPWCkcweGUwvbGlRKw%3D&from=3218412987","https://p6-sign.douyinpic.com/tos-cn-p-0015/33daffcff1e840799f8b5353159fd1dd_1660704795~noop.jpeg?x-expires=1660759200&x-signature=1q5rCMB0nSL6n4A4W4CurbK2cUM%3D&from=3218412987"]},"group_id":"7132653839228540172","sentence_id":"772628","related_words":null,"hotlist_param":"{\"version\":1}","word":"卫健委谈阻碍生育首要因素","hot_value":9420250,"position":11,"word_type":1,"view_count":50430460,"aweme_infos":null,"article_detail_count":0,"event_time":1660705775,"sentence_tag":3001,"discuss_video_count":1,"emo_label":0},{"video_count":3,"group_id":"7131754099885823245","sentence_id":"772982","word_sub_board":null,"emo_label":0,"word":"浙江一天减少超1亿立方水","drift_info":null,"hotlist_param":"{\"version\":1}","sentence_tag":22001,"article_detail_count":0,"challenge_id":"","position":12,"word_type":1,"event_time":1660717946,"view_count":54913498,"aweme_infos":null,"discuss_video_count":1,"label":0,"word_cover":{"uri":"tos-cn-p-0015/634f10659f2a47ac859b9da9912f592e","url_list":["https://p9-sign.douyinpic.com/tos-cn-p-0015/634f10659f2a47ac859b9da9912f592e~noop.jpeg?x-expires=1660759200&x-signature=AyvqAmJtKSeXxuGEo4%2BzsYol6zI%3D&from=3218412987","https://p3-sign.douyinpic.com/tos-cn-p-0015/634f10659f2a47ac859b9da9912f592e~noop.jpeg?x-expires=1660759200&x-signature=6kdbdPa4SIA6zeXnJvG1PghC48k%3D&from=3218412987","https://p26-sign.douyinpic.com/tos-cn-p-0015/634f10659f2a47ac859b9da9912f592e~noop.jpeg?x-expires=1660759200&x-signature=S8%2BiKpD1U9rY0RE32RmkOPgjCMk%3D&from=3218412987"]},"related_words":null,"hot_value":9361518},{"video_count":2,"group_id":"7131875926510441765","event_time":1660720230,"related_words":null,"sentence_tag":6000,"discuss_video_count":1,"challenge_id":"","position":13,"sentence_id":"773041","word_sub_board":null,"article_detail_count":0,"word":"苹果欲在越南生产电脑手表","word_cover":{"uri":"tos-cn-p-0015/3a85f79f4aff4f2ea03ea9fa63c5c629_1660705016","url_list":["https://p9-sign.douyinpic.com/tos-cn-p-0015/3a85f79f4aff4f2ea03ea9fa63c5c629_1660705016~noop.jpeg?x-expires=1660759200&x-signature=KHip37Va%2BRzomU0cUywXUN1gwPU%3D&from=3218412987","https://p6-sign.douyinpic.com/tos-cn-p-0015/3a85f79f4aff4f2ea03ea9fa63c5c629_1660705016~noop.jpeg?x-expires=1660759200&x-signature=6ev%2BO013p0LS%2B1WuCapVlZWrhB0%3D&from=3218412987","https://p26-sign.douyinpic.com/tos-cn-p-0015/3a85f79f4aff4f2ea03ea9fa63c5c629_1660705016~noop.jpeg?x-expires=1660759200&x-signature=NOHixxw%2F7bCef7dur6VB7TqDPgw%3D&from=3218412987"]},"word_type":1,"view_count":48704593,"hotlist_param":"{\"version\":1}","aweme_infos":null,"label":3,"hot_value":9346501,"drift_info":null},{"video_count":4,"event_time":1660706905,"article_detail_count":0,"drift_info":null,"hotlist_param":"{\"version\":1}","word":"劳荣枝案被害人之妻发声","word_cover":{"uri":"tos-cn-p-0015/cb408245d3b54d3f820b0d9d7e2b448f_1660707295","url_list":["https://p6-sign.douyinpic.com/tos-cn-p-0015/cb408245d3b54d3f820b0d9d7e2b448f_1660707295~noop.jpeg?x-expires=1660759200&x-signature=Ax9yVUpztUi7MMUndpT1vIcuYMI%3D&from=3218412987","https://p26-sign.douyinpic.com/tos-cn-p-0015/cb408245d3b54d3f820b0d9d7e2b448f_1660707295~noop.jpeg?x-expires=1660759200&x-signature=6Aehd8CmsV%2FxhVz%2FDLAQEl5t2vU%3D&from=3218412987","https://p3-sign.douyinpic.com/tos-cn-p-0015/cb408245d3b54d3f820b0d9d7e2b448f_1660707295~noop.jpeg?x-expires=1660759200&x-signature=K7r06MbftUNfskYvxbS%2FoZl5hVk%3D&from=3218412987"]},"group_id":"7132109198411207970","sentence_id":"772664","related_words":null,"view_count":46244964,"discuss_video_count":1,"position":14,"can_extend_detail":false,"sentence_tag":4003,"word_sub_board":null,"label":3,"hot_value":9307348,"challenge_id":"","word_type":1,"aweme_infos":null,"display_style":0},{"hotlist_param":"{\"version\":1}","discuss_video_count":1,"word":"未婚已育女性正常享受生育津贴","hot_value":8866081,"challenge_id":"","position":15,"word_type":1,"drift_info":null,"view_count":48052942,"sentence_tag":4003,"video_count":1,"sentence_id":"773443","event_time":1660732205,"related_words":null,"aweme_infos":null,"word_sub_board":null,"article_detail_count":1,"label":1,"word_cover":{"uri":"tos-cn-p-0015/f87627b10a944c67b45c483e72cb998a_1660731242","url_list":["https://p3-sign.douyinpic.com/tos-cn-p-0015/f87627b10a944c67b45c483e72cb998a_1660731242~noop.jpeg?x-expires=1660759200&x-signature=gZ5CLA%2FT0EQXnJrvvBSdSqMR7CM%3D&from=3218412987","https://p9-sign.douyinpic.com/tos-cn-p-0015/f87627b10a944c67b45c483e72cb998a_1660731242~noop.jpeg?x-expires=1660759200&x-signature=EDZZ7Z8DnTVmYoXPwK%2B53QjOz3I%3D&from=3218412987","https://p26-sign.douyinpic.com/tos-cn-p-0015/f87627b10a944c67b45c483e72cb998a_1660731242~noop.jpeg?x-expires=1660759200&x-signature=%2B%2B4k1gm%2BdHjaCH3nyhSo8EpdK2Y%3D&from=3218412987"]},"group_id":"7131782155064579339"},{"position":16,"video_count":3,"sentence_id":"773049","aweme_infos":null,"sentence_tag":4005,"word_sub_board":null,"hot_value":8837767,"word_cover":{"uri":"tos-cn-p-0015/8018d743f14a450fb734f5089dc38b08_1660719854","url_list":["https://p6-sign.douyinpic.com/tos-cn-p-0015/8018d743f14a450fb734f5089dc38b08_1660719854~noop.jpeg?x-expires=1660759200&x-signature=Z2Q%2FVPbr6ZctdIiWhoEPmB9q5XU%3D&from=3218412987","https://p9-sign.douyinpic.com/tos-cn-p-0015/8018d743f14a450fb734f5089dc38b08_1660719854~noop.jpeg?x-expires=1660759200&x-signature=yJjmDTz2BCK8amVZxWbRoFsRUok%3D&from=3218412987","https://p26-sign.douyinpic.com/tos-cn-p-0015/8018d743f14a450fb734f5089dc38b08_1660719854~noop.jpeg?x-expires=1660759200&x-signature=8O1jqBI4tw2tl4otLBwauyhduTg%3D&from=3218412987"]},"view_count":45052272,"hotlist_param":"{\"version\":1}","group_id":"7131882841097409803","word_type":1,"related_words":null,"drift_info":null,"discuss_video_count":1,"challenge_id":"","event_time":1660720519,"article_detail_count":0,"word":"厦门集美鱼虾也要做核酸","label":3},{"word_sub_board":null,"word":"小豪孙秀这次真的he了","challenge_id":"","position":17,"group_id":"7132384731706316065","event_time":1660715922,"drift_info":null,"aweme_infos":null,"article_detail_count":0,"emo_label":0,"word_cover":{"uri":"tos-cn-p-0015/d4c1123807574ff4b21d6031ef4ab55b","url_list":["https://p3-sign.douyinpic.com/tos-cn-p-0015/d4c1123807574ff4b21d6031ef4ab55b~noop.jpeg?x-expires=1660759200&x-signature=q0TPNEc%2BOCaNP94I3nVTo2zjeGg%3D&from=3218412987","https://p26-sign.douyinpic.com/tos-cn-p-0015/d4c1123807574ff4b21d6031ef4ab55b~noop.jpeg?x-expires=1660759200&x-signature=Z4nzFeEV7SohgZ8%2Beb0KNPtG4VA%3D&from=3218412987","https://p6-sign.douyinpic.com/tos-cn-p-0015/d4c1123807574ff4b21d6031ef4ab55b~noop.jpeg?x-expires=1660759200&x-signature=VSgHjitMHf3e94F8I1MTdYisUr4%3D&from=3218412987"]},"video_count":6,"word_type":1,"related_words":null,"discuss_video_count":1,"label":5,"hot_value":8742292,"can_extend_detail":false,"sentence_id":"772901","view_count":41656270,"hotlist_param":"{\"version\":1}","sentence_tag":2003},{"discuss_video_count":1,"article_detail_count":1,"view_count":42110273,"hot_value":8673581,"position":18,"drift_info":null,"hotlist_param":"{\"version\":1}","sentence_tag":4003,"word_sub_board":null,"word":"男孩关停扶梯致女童摔下","sentence_id":"772858","related_words":null,"label":0,"word_cover":{"url_list":["https://p26-sign.douyinpic.com/tos-cn-p-0015/87f30bac1ac042f5a915348a9cb8dcde~noop.jpeg?x-expires=1660759200&x-signature=xYNUM%2BPAfPKIiIJHkrXeWDxPACc%3D&from=3218412987","https://p3-sign.douyinpic.com/tos-cn-p-0015/87f30bac1ac042f5a915348a9cb8dcde~noop.jpeg?x-expires=1660759200&x-signature=6U4BiNCptWlR6QNDHX7JEvFDtMA%3D&from=3218412987","https://p9-sign.douyinpic.com/tos-cn-p-0015/87f30bac1ac042f5a915348a9cb8dcde~noop.jpeg?x-expires=1660759200&x-signature=BTBuOC8pPnXc2CPFNPvJdG%2FcN7s%3D&from=3218412987"],"uri":"tos-cn-p-0015/87f30bac1ac042f5a915348a9cb8dcde"},"video_count":2,"group_id":"7131913589102990628","word_type":1,"event_time":1660714744,"aweme_infos":null,"challenge_id":""},{"position":19,"article_detail_count":0,"emo_label":0,"word_cover":{"uri":"tos-cn-p-0015/4afdd32044234ada82424573f6ddd870","url_list":["https://p9-sign.douyinpic.com/tos-cn-p-0015/4afdd32044234ada82424573f6ddd870~noop.jpeg?x-expires=1660759200&x-signature=4Ht5nls8RHm90h4sJmevtKkKTaA%3D&from=3218412987","https://p6-sign.douyinpic.com/tos-cn-p-0015/4afdd32044234ada82424573f6ddd870~noop.jpeg?x-expires=1660759200&x-signature=Uf22SCl0EOlNEqM2FnyJT63H85k%3D&from=3218412987","https://p3-sign.douyinpic.com/tos-cn-p-0015/4afdd32044234ada82424573f6ddd870~noop.jpeg?x-expires=1660759200&x-signature=%2B4eC8GJfH%2FFlq4oBXhw9qLSP4tI%3D&from=3218412987"]},"hotlist_param":"{\"version\":1}","sentence_tag":4004,"word_sub_board":null,"word_type":1,"sentence_id":"772812","related_words":null,"aweme_infos":null,"word":"男孩梦到过世爷爷掩面痛哭","label":3,"challenge_id":"","video_count":3,"drift_info":null,"discuss_video_count":1,"hot_value":8652669,"group_id":"7131892426591294728","event_time":1660713089,"view_count":37627462},{"word":"茶百道 垫底辣孩","label":3,"hot_value":8536161,"sentence_id":"772720","event_time":1660709228,"challenge_id":"","position":20,"group_id":"7131928732856374562","related_words":null,"drift_info":null,"sentence_tag":20003,"article_detail_count":0,"emo_label":0,"word_cover":{"uri":"tos-cn-p-0015/f4f70b633f6e47759f1259f0163c67be","url_list":["https://p3-sign.douyinpic.com/tos-cn-p-0015/f4f70b633f6e47759f1259f0163c67be~noop.jpeg?x-expires=1660759200&x-signature=gV98KFzKzOCOy2P6yvu4HAKEprQ%3D&from=3218412987","https://p9-sign.douyinpic.com/tos-cn-p-0015/f4f70b633f6e47759f1259f0163c67be~noop.jpeg?x-expires=1660759200&x-signature=ZuzHT4FS1iNSZ6fxfYv36SfWBi4%3D&from=3218412987","https://p26-sign.douyinpic.com/tos-cn-p-0015/f4f70b633f6e47759f1259f0163c67be~noop.jpeg?x-expires=1660759200&x-signature=FMjXd5vNkODVFu8ZqL7pMU%2BskOI%3D&from=3218412987"]},"video_count":9,"word_type":1,"view_count":42136789,"aweme_infos":null,"discuss_video_count":1,"can_extend_detail":false,"hotlist_param":"{\"version\":1}","display_style":0,"word_sub_board":null},{"sentence_id":"772643","event_time":1660706384,"drift_info":null,"emo_label":0,"word":"吕一老公钱泳辰被曝骗学费","label":3,"group_id":"7131716505066673408","can_extend_detail":false,"challenge_id":"","word_cover":{"url_list":["https://p26-sign.douyinpic.com/tos-cn-p-0015/6b49c3e76f524993977180c6ed1a102d~noop.jpeg?x-expires=1660759200&x-signature=HyIzmTYZdU9AYR1g8ZTMHILvohM%3D&from=3218412987","https://p3-sign.douyinpic.com/tos-cn-p-0015/6b49c3e76f524993977180c6ed1a102d~noop.jpeg?x-expires=1660759200&x-signature=OG6yVb67cBp7h9uw%2BPNsEQ5k6fM%3D&from=3218412987","https://p6-sign.douyinpic.com/tos-cn-p-0015/6b49c3e76f524993977180c6ed1a102d~noop.jpeg?x-expires=1660759200&x-signature=0YlqmJqnlfj5ZgOG1Mg%2BTFsVfH0%3D&from=3218412987"],"uri":"tos-cn-p-0015/6b49c3e76f524993977180c6ed1a102d"},"sentence_tag":2009,"word_sub_board":null,"hot_value":8437035,"word_type":1,"display_style":0,"discuss_video_count":1,"hotlist_param":"{\"version\":1}","aweme_infos":null,"article_detail_count":0,"position":21,"video_count":3,"related_words":null,"view_count":39871328},{"emo_label":0,"label":3,"hot_value":8347685,"challenge_id":"","view_count":37720251,"aweme_infos":null,"word_sub_board":null,"article_detail_count":0,"position":22,"word_type":1,"related_words":null,"drift_info":null,"video_count":5,"group_id":"7131203463943525645","sentence_id":"772538","hotlist_param":"{\"version\":1}","sentence_tag":8000,"discuss_video_count":1,"word":"大连首次发现桃花水母","word_cover":{"uri":"tos-cn-p-0015/bb2683c5e3b14e54a3d317df88b2561c","url_list":["https://p26-sign.douyinpic.com/tos-cn-p-0015/bb2683c5e3b14e54a3d317df88b2561c~noop.jpeg?x-expires=1660759200&x-signature=oKMyolmcPzc0XiEuiosnIuHs%2BhQ%3D&from=3218412987","https://p6-sign.douyinpic.com/tos-cn-p-0015/bb2683c5e3b14e54a3d317df88b2561c~noop.jpeg?x-expires=1660759200&x-signature=%2B%2B7yP8tXlT0XnmmBKgf65DuMtss%3D&from=3218412987","https://p3-sign.douyinpic.com/tos-cn-p-0015/bb2683c5e3b14e54a3d317df88b2561c~noop.jpeg?x-expires=1660759200&x-signature=xi3UVZUgRib5E%2BdPBefBWPwfx%2Fc%3D&from=3218412987"]},"can_extend_detail":false,"event_time":1660702432},{"event_time":1660658424,"article_detail_count":0,"aweme_infos":null,"sentence_tag":4003,"emo_label":0,"hot_value":8287683,"word_cover":{"uri":"tos-cn-p-0015/6e194420c4344df397e01e745021656a","url_list":["https://p3-sign.douyinpic.com/tos-cn-p-0015/6e194420c4344df397e01e745021656a~noop.jpeg?x-expires=1660759200&x-signature=WqYwQK02TAV8%2B%2BZ%2F9JKcxE1QLpY%3D&from=3218412987","https://p26-sign.douyinpic.com/tos-cn-p-0015/6e194420c4344df397e01e745021656a~noop.jpeg?x-expires=1660759200&x-signature=zKJOB8STt4s1ddD9NYiTn7kVHKI%3D&from=3218412987","https://p6-sign.douyinpic.com/tos-cn-p-0015/6e194420c4344df397e01e745021656a~noop.jpeg?x-expires=1660759200&x-signature=qePxLjv9dCINRJ9W9GDhElAh4wU%3D&from=3218412987"]},"word_type":1,"related_words":null,"view_count":36386522,"challenge_id":"","sentence_id":"772217","hotlist_param":"{\"version\":1}","discuss_video_count":1,"word_sub_board":null,"drift_info":null,"word":"2岁女童遭蛇咬后咬死蛇","label":3,"position":23,"video_count":5,"group_id":"7132003490393855267"},{"video_count":2,"word_type":1,"word_sub_board":null,"article_detail_count":1,"hot_value":8277249,"word_cover":{"uri":"tos-cn-p-0015/bf13c0eae98f4261814de546469c07e2_1660704141","url_list":["https://p3-sign.douyinpic.com/tos-cn-p-0015/bf13c0eae98f4261814de546469c07e2_1660704141~noop.jpeg?x-expires=1660759200&x-signature=K14S60f5PsTEcu3jSNdqZU5JYgI%3D&from=3218412987","https://p9-sign.douyinpic.com/tos-cn-p-0015/bf13c0eae98f4261814de546469c07e2_1660704141~noop.jpeg?x-expires=1660759200&x-signature=mfmv%2F1PjFrXo8YMxW0jQ75dl3mk%3D&from=3218412987","https://p6-sign.douyinpic.com/tos-cn-p-0015/bf13c0eae98f4261814de546469c07e2_1660704141~noop.jpeg?x-expires=1660759200&x-signature=NRA5j1lx6%2B9FAu1TZ%2F6c02WiKhk%3D&from=3218412987"]},"group_id":"7132383820444226854","hotlist_param":"{\"version\":1}","aweme_infos":null,"discuss_video_count":1,"sentence_tag":7000,"word":"东部4省要完成财政上缴任务","label":3,"challenge_id":"","position":24,"view_count":37594358,"drift_info":null,"sentence_id":"772627","event_time":1660705578,"related_words":null,"display_style":0},{"group_id":"6975162905298113799","related_words":null,"drift_info":null,"discuss_video_count":1,"word_sub_board":null,"label":3,"word_cover":{"uri":"tos-cn-p-0015/a2388f3c69554bd1aa6c0f262e11e52e_1660691188","url_list":["https://p3-sign.douyinpic.com/tos-cn-p-0015/a2388f3c69554bd1aa6c0f262e11e52e_1660691188~noop.jpeg?x-expires=1660759200&x-signature=sNZ0GSP8JHcH1FmGSUcKz0TmVuo%3D&from=3218412987","https://p6-sign.douyinpic.com/tos-cn-p-0015/a2388f3c69554bd1aa6c0f262e11e52e_1660691188~noop.jpeg?x-expires=1660759200&x-signature=t469rz38IKdbGtczQSVFIppM4J0%3D&from=3218412987","https://p9-sign.douyinpic.com/tos-cn-p-0015/a2388f3c69554bd1aa6c0f262e11e52e_1660691188~noop.jpeg?x-expires=1660759200&x-signature=KfaGKVYE28U%2FpB6wabyZDfFUZ3s%3D&from=3218412987"]},"article_detail_count":0,"emo_label":0,"hot_value":7934342,"event_time":1660693742,"word_type":1,"view_count":30447738,"position":25,"video_count":5,"sentence_id":"772347","hotlist_param":"{\"version\":1}","aweme_infos":null,"sentence_tag":14000,"word":"多所高校发布延迟开学通知","challenge_id":""},{"position":26,"event_time":1660706465,"related_words":null,"view_count":30526772,"aweme_infos":null,"challenge_id":"","word_cover":{"uri":"tos-cn-p-0015/d55844c00964453c96675a1bee9f747d_1660707426","url_list":["https://p9-sign.douyinpic.com/tos-cn-p-0015/d55844c00964453c96675a1bee9f747d_1660707426~noop.jpeg?x-expires=1660759200&x-signature=sfSMM7JcGxN95M48bt4QGfSbG%2F8%3D&from=3218412987","https://p6-sign.douyinpic.com/tos-cn-p-0015/d55844c00964453c96675a1bee9f747d_1660707426~noop.jpeg?x-expires=1660759200&x-signature=C%2FpxWg%2FLnGuMW5yUpxnvONLqtiE%3D&from=3218412987","https://p3-sign.douyinpic.com/tos-cn-p-0015/d55844c00964453c96675a1bee9f747d_1660707426~noop.jpeg?x-expires=1660759200&x-signature=7GwUZweg1YA9zKiriTdUsBKYPlQ%3D&from=3218412987"]},"video_count":4,"discuss_video_count":1,"emo_label":0,"word":"成都写字楼限电停止供冷","label":3,"drift_info":null,"hotlist_param":"{\"version\":1}","word_sub_board":null,"article_detail_count":0,"hot_value":7911807,"group_id":"7131731843996898598","word_type":1,"sentence_id":"772647","sentence_tag":4003},{"word_cover":{"uri":"tos-cn-p-0015/881e766e63a94dbeae5ada9264855db7_1660734339","url_list":["https://p3-sign.douyinpic.com/tos-cn-p-0015/881e766e63a94dbeae5ada9264855db7_1660734339~noop.jpeg?x-expires=1660759200&x-signature=H%2BYv%2BtAKw%2BBy%2B2c1XsI%2FfbT7UlA%3D&from=3218412987","https://p26-sign.douyinpic.com/tos-cn-p-0015/881e766e63a94dbeae5ada9264855db7_1660734339~noop.jpeg?x-expires=1660759200&x-signature=BMB6ZoHE3fozlSsVS1tQCarfa3k%3D&from=3218412987","https://p9-sign.douyinpic.com/tos-cn-p-0015/881e766e63a94dbeae5ada9264855db7_1660734339~noop.jpeg?x-expires=1660759200&x-signature=bSqY5JRh%2FhHHZVXZzCLI4t0q2RE%3D&from=3218412987"]},"group_id":"7131912208083145991","can_extend_detail":false,"sentence_id":"773521","word":"披荆斩棘819首播","hot_value":7895076,"sentence_tag":2003,"discuss_video_count":1,"position":27,"aweme_infos":null,"word_type":1,"related_words":null,"view_count":32714490,"article_detail_count":0,"challenge_id":"","video_count":4,"drift_info":null,"hotlist_param":"{\"version\":1}","word_sub_board":null,"label":0,"event_time":1660734816},{"label":3,"sentence_id":"773201","event_time":1660725896,"view_count":26577050,"discuss_video_count":1,"word":"北京新增本土3+1","hot_value":7780604,"word_cover":{"url_list":["https://p26-sign.douyinpic.com/tos-cn-p-0015/5c34af96700f463694db007dc6ed3c2b~noop.jpeg?x-expires=1660759200&x-signature=8dVN%2Bqcxe7lWhepRrkw1tjEaEVQ%3D&from=3218412987","https://p9-sign.douyinpic.com/tos-cn-p-0015/5c34af96700f463694db007dc6ed3c2b~noop.jpeg?x-expires=1660759200&x-signature=jHf8HHXiz%2BooucL8tbZhFW1uLNA%3D&from=3218412987","https://p3-sign.douyinpic.com/tos-cn-p-0015/5c34af96700f463694db007dc6ed3c2b~noop.jpeg?x-expires=1660759200&x-signature=k%2Btqvm3ega5XyZAsXn1oQkJ%2F1tI%3D&from=3218412987"],"uri":"tos-cn-p-0015/5c34af96700f463694db007dc6ed3c2b"},"position":28,"group_id":"7058068458882192673","drift_info":null,"aweme_infos":null,"video_count":3,"related_words":null,"hotlist_param":"{\"version\":1}","sentence_tag":4005,"word_sub_board":null,"article_detail_count":0,"challenge_id":"","word_type":1},{"group_id":"7131866183175116069","event_time":1660657990,"view_count":27717252,"discuss_video_count":1,"emo_label":0,"hot_value":7747117,"hotlist_param":"{\"version\":1}","word":"LOL非活跃账号将被删除","challenge_id":"","position":29,"video_count":4,"sentence_id":"772208","related_words":null,"drift_info":null,"aweme_infos":null,"word_sub_board":null,"article_detail_count":0,"label":3,"word_cover":{"uri":"tos-cn-p-0015/53e22a418c174f10a567df1418520be7","url_list":["https://p3-sign.douyinpic.com/tos-cn-p-0015/53e22a418c174f10a567df1418520be7~noop.jpeg?x-expires=1660759200&x-signature=5bsn2Q6%2BI%2BGIRr8GoHzUMCNZ8rs%3D&from=3218412987","https://p9-sign.douyinpic.com/tos-cn-p-0015/53e22a418c174f10a567df1418520be7~noop.jpeg?x-expires=1660759200&x-signature=jETlFMnHJ9DTRUmvrdHkpld0hJs%3D&from=3218412987","https://p6-sign.douyinpic.com/tos-cn-p-0015/53e22a418c174f10a567df1418520be7~noop.jpeg?x-expires=1660759200&x-signature=KeWp%2ByRD6vrGYQwaC8uTH5LnCuE%3D&from=3218412987"]},"word_type":1,"sentence_tag":12000},{"view_count":25555180,"hotlist_param":"{\"version\":1}","sentence_tag":2002,"word_sub_board":null,"emo_label":0,"aweme_infos":null,"article_detail_count":0,"word":"唐周主动吻颜淡","position":30,"video_count":4,"group_id":"7128721274209162507","event_time":1660692526,"drift_info":null,"challenge_id":"","can_extend_detail":false,"related_words":null,"label":3,"hot_value":7740923,"word_cover":{"uri":"tos-cn-p-0015/46a9b9f117f34663ba25fd20940f55c1_1660628978","url_list":["https://p3-sign.douyinpic.com/tos-cn-p-0015/46a9b9f117f34663ba25fd20940f55c1_1660628978~noop.jpeg?x-expires=1660759200&x-signature=KAOZbi5Jcj3eiJRfDrsa8SIabv8%3D&from=3218412987","https://p9-sign.douyinpic.com/tos-cn-p-0015/46a9b9f117f34663ba25fd20940f55c1_1660628978~noop.jpeg?x-expires=1660759200&x-signature=nwNxmc4VDSGpCFNK18Amuv3k8I4%3D&from=3218412987","https://p26-sign.douyinpic.com/tos-cn-p-0015/46a9b9f117f34663ba25fd20940f55c1_1660628978~noop.jpeg?x-expires=1660759200&x-signature=NIgoB4UblM5qRqJ1YIL9VPifLz8%3D&from=3218412987"]},"word_type":1,"sentence_id":"772321","discuss_video_count":1},{"sentence_id":"772463","display_style":0,"article_detail_count":0,"label":3,"position":31,"group_id":"7131864579474232607","can_extend_detail":false,"drift_info":null,"sentence_tag":4005,"word_sub_board":null,"hot_value":7607450,"word_cover":{"uri":"tos-cn-p-0015/01add8073dcf46a4a27a6e04a284f166","url_list":["https://p26-sign.douyinpic.com/tos-cn-p-0015/01add8073dcf46a4a27a6e04a284f166~noop.jpeg?x-expires=1660759200&x-signature=8gRf2zQRV8gz%2BivF3UKW8x6s6KY%3D&from=3218412987","https://p9-sign.douyinpic.com/tos-cn-p-0015/01add8073dcf46a4a27a6e04a284f166~noop.jpeg?x-expires=1660759200&x-signature=PthhjfHGA374bXzYUV%2FjeZD67Yo%3D&from=3218412987","https://p3-sign.douyinpic.com/tos-cn-p-0015/01add8073dcf46a4a27a6e04a284f166~noop.jpeg?x-expires=1660759200&x-signature=58A7oy4Eiqyer52MkD9%2FE%2B9zpwE%3D&from=3218412987"]},"video_count":5,"event_time":1660699340,"related_words":null,"aweme_infos":null,"discuss_video_count":1,"emo_label":0,"word":"31省区市新增566+2322","challenge_id":"","word_type":1,"view_count":22041370,"hotlist_param":"{\"version\":1}"},{"word":"当事人回应劝阻熊孩子被怼","label":0,"word_type":1,"sentence_id":"773139","view_count":23879411,"challenge_id":"","word_cover":{"uri":"tos-cn-p-0015/d04d1da493c64d4b82b832820e19e9dc","url_list":["https://p26-sign.douyinpic.com/tos-cn-p-0015/d04d1da493c64d4b82b832820e19e9dc~noop.jpeg?x-expires=1660759200&x-signature=CbO9fmuG7iClzRQ5zTIiaATE%2F9c%3D&from=3218412987","https://p6-sign.douyinpic.com/tos-cn-p-0015/d04d1da493c64d4b82b832820e19e9dc~noop.jpeg?x-expires=1660759200&x-signature=%2FbRIWaxljKcbMBYdVuz3dqRCozA%3D&from=3218412987","https://p3-sign.douyinpic.com/tos-cn-p-0015/d04d1da493c64d4b82b832820e19e9dc~noop.jpeg?x-expires=1660759200&x-signature=4WMK4rkojAJCtv33FxGktO%2Bctrg%3D&from=3218412987"]},"event_time":1660724096,"drift_info":null,"article_detail_count":1,"discuss_video_count":1,"word_sub_board":null,"position":32,"video_count":6,"group_id":"7131913019315246344","aweme_infos":null,"sentence_tag":4003,"hot_value":7540852,"related_words":null,"hotlist_param":"{\"version\":1}"},{"hot_value":7528656,"word_type":1,"sentence_tag":4003,"sentence_id":"773130","drift_info":null,"discuss_video_count":1,"word_sub_board":null,"word":"四川水电能力下降超5成","label":3,"word_cover":{"url_list":["https://p3-sign.douyinpic.com/tos-cn-p-0015/c9e37041da2a489abeabc9e63afb47e1~noop.jpeg?x-expires=1660759200&x-signature=Li3tX%2BmAnYIPhBRUVbxsuLZGXyo%3D&from=3218412987","https://p26-sign.douyinpic.com/tos-cn-p-0015/c9e37041da2a489abeabc9e63afb47e1~noop.jpeg?x-expires=1660759200&x-signature=X4QE3q%2BEmRsD8lgJehY8KhYF%2Fs4%3D&from=3218412987","https://p6-sign.douyinpic.com/tos-cn-p-0015/c9e37041da2a489abeabc9e63afb47e1~noop.jpeg?x-expires=1660759200&x-signature=JJaME9fGxTGbMX0FjMmmRlLa%2BpY%3D&from=3218412987"],"uri":"tos-cn-p-0015/c9e37041da2a489abeabc9e63afb47e1"},"position":33,"event_time":1660723420,"related_words":null,"view_count":21220953,"aweme_infos":null,"article_detail_count":1,"challenge_id":"","video_count":4,"group_id":"7132386441693271300","hotlist_param":"{\"version\":1}"},{"word_sub_board":null,"article_detail_count":0,"hot_value":7515739,"word_cover":{"uri":"tos-cn-p-0015/5e5bdaa62e2546ecbfe4a080b9de5737_1660731193","url_list":["https://p6-sign.douyinpic.com/tos-cn-p-0015/5e5bdaa62e2546ecbfe4a080b9de5737_1660731193~noop.jpeg?x-expires=1660759200&x-signature=MqQspiHSCcEM8zAIGJyyntW50UQ%3D&from=3218412987","https://p3-sign.douyinpic.com/tos-cn-p-0015/5e5bdaa62e2546ecbfe4a080b9de5737_1660731193~noop.jpeg?x-expires=1660759200&x-signature=ZiuEVR%2BHq7nV%2FHSSPVlc%2FI1x6Bs%3D&from=3218412987","https://p9-sign.douyinpic.com/tos-cn-p-0015/5e5bdaa62e2546ecbfe4a080b9de5737_1660731193~noop.jpeg?x-expires=1660759200&x-signature=tNIFf0CxwjvACtc0OiWa8c8u848%3D&from=3218412987"]},"word_type":1,"sentence_tag":4003,"discuss_video_count":1,"event_time":1660735171,"view_count":21438067,"drift_info":null,"hotlist_param":"{\"version\":1}","aweme_infos":null,"video_count":1,"group_id":"7131847234040452384","sentence_id":"773527","related_words":null,"word":"湘潭大学回应强制换寝","label":1,"challenge_id":"","position":34},{"word":"北京鼓励明日错峰上下班","word_cover":{"uri":"tos-cn-p-0015/8294bf0dd4ba43eab69220f35641de68","url_list":["https://p9-sign.douyinpic.com/tos-cn-p-0015/8294bf0dd4ba43eab69220f35641de68~noop.jpeg?x-expires=1660759200&x-signature=%2B2Li8EFjWKIADclf0UNCHw8NUcE%3D&from=3218412987","https://p26-sign.douyinpic.com/tos-cn-p-0015/8294bf0dd4ba43eab69220f35641de68~noop.jpeg?x-expires=1660759200&x-signature=jjM3iKzuFkB0YCuaUTATtJWUNlM%3D&from=3218412987","https://p3-sign.douyinpic.com/tos-cn-p-0015/8294bf0dd4ba43eab69220f35641de68~noop.jpeg?x-expires=1660759200&x-signature=QN0zhe4Rxa%2FD4J14i7V%2Bcd59MBw%3D&from=3218412987"]},"video_count":1,"event_time":1660731640,"view_count":21169190,"discuss_video_count":1,"label":1,"challenge_id":"","position":35,"related_words":null,"drift_info":null,"hotlist_param":"{\"version\":1}","hot_value":7414704,"group_id":"7131781131460318496","aweme_infos":null,"word_type":1,"sentence_id":"773418","sentence_tag":4003,"word_sub_board":null,"article_detail_count":0},{"position":36,"hotlist_param":"{\"version\":1}","hot_value":7390751,"word_type":1,"sentence_id":"773007","related_words":null,"discuss_video_count":1,"word_sub_board":null,"article_detail_count":2,"word":"让所有农村人口喝上放心水","challenge_id":"","view_count":17513816,"display_style":0,"label":3,"video_count":3,"group_id":"7131585704941425931","event_time":1660718745,"drift_info":null,"aweme_infos":null,"sentence_tag":4003,"emo_label":0,"word_cover":{"uri":"tos-cn-p-0015/e40be9d584f1475dae35af3adefd5ae3","url_list":["https://p9-sign.douyinpic.com/tos-cn-p-0015/e40be9d584f1475dae35af3adefd5ae3~noop.jpeg?x-expires=1660759200&x-signature=6lEvyVOrpyqQhEm20%2BixF4mt%2FJk%3D&from=3218412987","https://p3-sign.douyinpic.com/tos-cn-p-0015/e40be9d584f1475dae35af3adefd5ae3~noop.jpeg?x-expires=1660759200&x-signature=GvutCiQS9KXz%2BaL29KIjYbKD%2FoI%3D&from=3218412987","https://p26-sign.douyinpic.com/tos-cn-p-0015/e40be9d584f1475dae35af3adefd5ae3~noop.jpeg?x-expires=1660759200&x-signature=DOe4TcmGanMykJIZDpbW1Ghpp0I%3D&from=3218412987"]}},{"challenge_id":"","position":37,"can_extend_detail":false,"sentence_tag":2002,"discuss_video_count":1,"view_count":20167464,"hotlist_param":"{\"version\":1}","hot_value":7367197,"word_cover":{"uri":"tos-cn-p-0015/afafcd7035c444829ea3cb90e6290adb_1660724297","url_list":["https://p6-sign.douyinpic.com/tos-cn-p-0015/afafcd7035c444829ea3cb90e6290adb_1660724297~noop.jpeg?x-expires=1660759200&x-signature=nTle8uQAEactjmRSBRCEyAV5gZQ%3D&from=3218412987","https://p3-sign.douyinpic.com/tos-cn-p-0015/afafcd7035c444829ea3cb90e6290adb_1660724297~noop.jpeg?x-expires=1660759200&x-signature=f1Fw4VBY9e2E5sbGgrhwSML3%2Bqo%3D&from=3218412987","https://p9-sign.douyinpic.com/tos-cn-p-0015/afafcd7035c444829ea3cb90e6290adb_1660724297~noop.jpeg?x-expires=1660759200&x-signature=r%2FnDSOMGdfNFT0z1SJAC7XwaHfY%3D&from=3218412987"]},"group_id":"6986956584380536100","sentence_id":"773239","word_sub_board":null,"word":"沉香如屑颜淡恢复记忆","label":3,"video_count":16,"word_type":1,"event_time":1660726790,"related_words":null,"drift_info":null,"aweme_infos":null,"article_detail_count":0},{"word_cover":{"uri":"tos-cn-p-0015/9edd190682424503a35db06978645982_1660705583","url_list":["https://p26-sign.douyinpic.com/tos-cn-p-0015/9edd190682424503a35db06978645982_1660705583~noop.jpeg?x-expires=1660759200&x-signature=VDj80iCVeNqBZtHOC2iOmWnjyUE%3D&from=3218412987","https://p3-sign.douyinpic.com/tos-cn-p-0015/9edd190682424503a35db06978645982_1660705583~noop.jpeg?x-expires=1660759200&x-signature=HKerXNTresF7B1Og7IhIHIVT7cs%3D&from=3218412987","https://p9-sign.douyinpic.com/tos-cn-p-0015/9edd190682424503a35db06978645982_1660705583~noop.jpeg?x-expires=1660759200&x-signature=Y16AZlJEGpaNuFWYLzGUx6plWtE%3D&from=3218412987"]},"video_count":12,"group_id":"7132048472081224995","sentence_id":"773175","event_time":1660725255,"view_count":16749753,"word":"苍兰诀是昼川写的东方幻想吧","label":3,"drift_info":null,"aweme_infos":null,"article_detail_count":0,"hot_value":7362272,"can_extend_detail":false,"discuss_video_count":1,"word_sub_board":null,"related_words":null,"hotlist_param":"{\"version\":1}","word_type":1,"sentence_tag":2002,"challenge_id":"","position":38},{"label":3,"hot_value":7335404,"word_cover":{"uri":"tos-cn-p-0015/46c884e481af416fac981abac238981b_1660710549","url_list":["https://p3-sign.douyinpic.com/tos-cn-p-0015/46c884e481af416fac981abac238981b_1660710549~noop.jpeg?x-expires=1660759200&x-signature=354P7EfBWHshayMzPB3x7CRlwIM%3D&from=3218412987","https://p6-sign.douyinpic.com/tos-cn-p-0015/46c884e481af416fac981abac238981b_1660710549~noop.jpeg?x-expires=1660759200&x-signature=Go%2FBPlkiaQxTd92OEntLp%2F3IfoY%3D&from=3218412987","https://p9-sign.douyinpic.com/tos-cn-p-0015/46c884e481af416fac981abac238981b_1660710549~noop.jpeg?x-expires=1660759200&x-signature=dEU%2BjZGBD1mM4jkomX%2FpKb10gXg%3D&from=3218412987"]},"drift_info":null,"aweme_infos":null,"discuss_video_count":1,"sentence_id":"772767","event_time":1660711334,"related_words":null,"view_count":15075088,"word":"警方回应悬赏通缉75岁老人","challenge_id":"","word_type":1,"sentence_tag":4003,"display_style":0,"word_sub_board":null,"article_detail_count":0,"position":39,"video_count":5,"group_id":"7132246228625364256","hotlist_param":"{\"version\":1}"},{"position":40,"video_count":3,"group_id":"7131786220299883809","related_words":null,"drift_info":null,"hotlist_param":"{\"version\":1}","challenge_id":"","word_cover":{"uri":"tos-cn-p-0015/8b96bd928da84797867b33bfd9ddf5cd_1660723350","url_list":["https://p9-sign.douyinpic.com/tos-cn-p-0015/8b96bd928da84797867b33bfd9ddf5cd_1660723350~noop.jpeg?x-expires=1660759200&x-signature=Jtgv2uQg%2FyLL8W7Um1QQaOxDdGY%3D&from=3218412987","https://p3-sign.douyinpic.com/tos-cn-p-0015/8b96bd928da84797867b33bfd9ddf5cd_1660723350~noop.jpeg?x-expires=1660759200&x-signature=n0gO6BOlZeVZzKM2lF%2Flbj%2FbkfQ%3D&from=3218412987","https://p26-sign.douyinpic.com/tos-cn-p-0015/8b96bd928da84797867b33bfd9ddf5cd_1660723350~noop.jpeg?x-expires=1660759200&x-signature=s5VyfNII6QNpGKnkvTkKuO26jfc%3D&from=3218412987"]},"event_time":1660727850,"label":1,"word_type":1,"sentence_id":"773275","aweme_infos":null,"sentence_tag":4005,"word_sub_board":null,"article_detail_count":0,"word":"陕西疫情已报告阳性48例","hot_value":7240659,"view_count":13981961,"discuss_video_count":1},{"sentence_id":"772871","view_count":14093482,"drift_info":null,"sentence_tag":20005,"discuss_video_count":1,"word_sub_board":null,"article_detail_count":1,"word":"孩子闹高铁家长更有错","hot_value":7232924,"challenge_id":"","word_type":1,"aweme_infos":null,"label":0,"word_cover":{"url_list":["https://p3-sign.douyinpic.com/tos-cn-p-0015/7338be55fa6241e5864e9af3b45d8ac0~noop.jpeg?x-expires=1660759200&x-signature=tubYVXPj3wDVfcHUqPIAqhWhRUo%3D&from=3218412987","https://p26-sign.douyinpic.com/tos-cn-p-0015/7338be55fa6241e5864e9af3b45d8ac0~noop.jpeg?x-expires=1660759200&x-signature=PAlE4lTPPw4NGIYQbTTQFdvHjc4%3D&from=3218412987","https://p6-sign.douyinpic.com/tos-cn-p-0015/7338be55fa6241e5864e9af3b45d8ac0~noop.jpeg?x-expires=1660759200&x-signature=c9rEUY3nXfpDnaEfcSQtyge3o%2FQ%3D&from=3218412987"],"uri":"tos-cn-p-0015/7338be55fa6241e5864e9af3b45d8ac0"},"position":41,"group_id":"7131723714891633959","related_words":null,"video_count":24,"event_time":1660715060,"hotlist_param":"{\"version\":1}"},{"challenge_id":"","video_count":5,"word_type":1,"room_count":1,"aweme_infos":null,"discuss_video_count":1,"word_sub_board":null,"word_cover":{"uri":"tos-cn-p-0015/14288c6bb85f418399ae95c4eef2eb3c","url_list":["https://p26-sign.douyinpic.com/tos-cn-p-0015/14288c6bb85f418399ae95c4eef2eb3c~noop.jpeg?x-expires=1660759200&x-signature=PJYO%2BiEoTddgFlCPdCdNSpO7D%2BQ%3D&from=3218412987","https://p9-sign.douyinpic.com/tos-cn-p-0015/14288c6bb85f418399ae95c4eef2eb3c~noop.jpeg?x-expires=1660759200&x-signature=w2%2FW7W9gDrZc6CsTR5dLazdmKuc%3D&from=3218412987","https://p3-sign.douyinpic.com/tos-cn-p-0015/14288c6bb85f418399ae95c4eef2eb3c~noop.jpeg?x-expires=1660759200&x-signature=v8LsTxd9w2BL6gIgjVCOLusfwa0%3D&from=3218412987"]},"sentence_id":"772663","related_words":null,"sentence_tag":20003,"word":"四川人又在蹲萧敬腾了","label":3,"hot_value":7123233,"group_id":"7132059768513352994","event_time":1660706887,"view_count":10376641,"drift_info":null,"article_detail_count":0,"position":42,"hotlist_param":"{\"version\":1}"},{"article_detail_count":0,"label":0,"challenge_id":"","group_id":"7019568867517388066","word_type":1,"sentence_tag":4003,"word_sub_board":null,"word":"劳荣枝案二审明日开庭","hot_value":7119492,"video_count":6,"event_time":1660707671,"discuss_video_count":1,"position":43,"room_count":0,"related_words":null,"aweme_infos":null,"hotlist_param":"{\"version\":1}","word_cover":{"uri":"tos-cn-p-0015/e9b4e492646e4b669a1aeb0f37fe1ae1_1660638697","url_list":["https://p9-sign.douyinpic.com/tos-cn-p-0015/e9b4e492646e4b669a1aeb0f37fe1ae1_1660638697~noop.jpeg?x-expires=1660759200&x-signature=%2F38PQUUacx1vW5VMSxV9cDdlnZk%3D&from=3218412987","https://p3-sign.douyinpic.com/tos-cn-p-0015/e9b4e492646e4b669a1aeb0f37fe1ae1_1660638697~noop.jpeg?x-expires=1660759200&x-signature=xvph5Im%2B1f1J4MWF00G8y%2B3rpnI%3D&from=3218412987","https://p6-sign.douyinpic.com/tos-cn-p-0015/e9b4e492646e4b669a1aeb0f37fe1ae1_1660638697~noop.jpeg?x-expires=1660759200&x-signature=8%2Btck%2FDnA3GYS2HjXH8SAkrF1zU%3D&from=3218412987"]},"can_extend_detail":false,"sentence_id":"772683","view_count":9536830,"drift_info":null},{"word":"海南新增本土482+1181","hot_value":7088095,"challenge_id":"","view_count":7144237,"aweme_infos":null,"discuss_video_count":1,"article_detail_count":0,"position":44,"sentence_id":"772500","related_words":null,"sentence_tag":4005,"word_sub_board":null,"label":3,"word_cover":{"uri":"tos-cn-p-0015/e7912d2d115e4d6d814f1dae5aa116bf_1660700167","url_list":["https://p9-sign.douyinpic.com/tos-cn-p-0015/e7912d2d115e4d6d814f1dae5aa116bf_1660700167~noop.jpeg?x-expires=1660759200&x-signature=ZWti8bjICxB8RgXLDwZ0aYm3T8s%3D&from=3218412987","https://p3-sign.douyinpic.com/tos-cn-p-0015/e7912d2d115e4d6d814f1dae5aa116bf_1660700167~noop.jpeg?x-expires=1660759200&x-signature=rIwXsfk%2FHhPgR5NTZblfizsu%2BZQ%3D&from=3218412987","https://p26-sign.douyinpic.com/tos-cn-p-0015/e7912d2d115e4d6d814f1dae5aa116bf_1660700167~noop.jpeg?x-expires=1660759200&x-signature=nOo4UHrpH7Lo%2FI90YV%2Ft%2B%2Bc9Xdw%3D&from=3218412987"]},"video_count":5,"group_id":"7132101871594427684","word_type":1,"room_count":0,"event_time":1660700489,"drift_info":null,"hotlist_param":"{\"version\":1}"},{"challenge_id":"","group_id":"7132273305667736873","word":"广州天河区一商场被围蔽","label":0,"sentence_id":"772661","related_words":null,"view_count":6875463,"sentence_tag":4003,"word_sub_board":null,"article_detail_count":1,"word_cover":{"uri":"tos-cn-p-0015/74ecc0ed80364ae294e3c17b5fd89c80_1660705098","url_list":["https://p9-sign.douyinpic.com/tos-cn-p-0015/74ecc0ed80364ae294e3c17b5fd89c80_1660705098~noop.jpeg?x-expires=1660759200&x-signature=GgaxwjYTKDYzQftLiZXQzPDDTmY%3D&from=3218412987","https://p26-sign.douyinpic.com/tos-cn-p-0015/74ecc0ed80364ae294e3c17b5fd89c80_1660705098~noop.jpeg?x-expires=1660759200&x-signature=892xiwNvOBO10CBhDs%2FXq%2FbZ9Vo%3D&from=3218412987","https://p3-sign.douyinpic.com/tos-cn-p-0015/74ecc0ed80364ae294e3c17b5fd89c80_1660705098~noop.jpeg?x-expires=1660759200&x-signature=qg6kczwhE484bf7Jr9VBe9X%2BE2k%3D&from=3218412987"]},"position":45,"event_time":1660706798,"drift_info":null,"hotlist_param":"{\"version\":1}","hot_value":7082175,"word_type":1,"discuss_video_count":1,"video_count":2,"aweme_infos":null},{"label":3,"group_id":"7132383170209322251","event_time":1660698781,"article_detail_count":1,"aweme_infos":null,"word_sub_board":null,"word_cover":{"url_list":["https://p6-sign.douyinpic.com/tos-cn-p-0015/842f24c2a4f64f27aab0e7baacf0684c_1660491743~noop.jpeg?x-expires=1660759200&x-signature=6b476tlPv9ZmCRTJIWURGhQ7shg%3D&from=3218412987","https://p3-sign.douyinpic.com/tos-cn-p-0015/842f24c2a4f64f27aab0e7baacf0684c_1660491743~noop.jpeg?x-expires=1660759200&x-signature=Rd%2FVAJuCdFyHn1BH9QLcfvmApec%3D&from=3218412987","https://p9-sign.douyinpic.com/tos-cn-p-0015/842f24c2a4f64f27aab0e7baacf0684c_1660491743~noop.jpeg?x-expires=1660759200&x-signature=Z%2FeIgLhmHhD7Kk4SBwBdHFaN3do%3D&from=3218412987"],"uri":"tos-cn-p-0015/842f24c2a4f64f27aab0e7baacf0684c_1660491743"},"video_count":7,"word_type":1,"sentence_id":"772448","related_words":null,"view_count":7596904,"word":"孩子高铁吵闹乘客提醒反被怼","challenge_id":"","hotlist_param":"{\"version\":1}","sentence_tag":4003,"discuss_video_count":1,"emo_label":0,"hot_value":7042102,"position":46,"drift_info":null},{"can_extend_detail":false,"sentence_id":"772614","sentence_tag":2001,"hotlist_param":"{\"version\":1}","discuss_video_count":1,"word_sub_board":null,"video_count":5,"related_words":null,"view_count":4398481,"article_detail_count":0,"word":"大圣归来导演新作深海","challenge_id":"","aweme_infos":null,"position":47,"group_id":"6898304570066212109","word_type":1,"event_time":1660705284,"drift_info":null,"label":3,"hot_value":6953958,"word_cover":{"uri":"tos-cn-p-0015/0ed43b878b1c4e2f80b8408b6efa6daf_1660701991","url_list":["https://p3-sign.douyinpic.com/tos-cn-p-0015/0ed43b878b1c4e2f80b8408b6efa6daf_1660701991~noop.jpeg?x-expires=1660759200&x-signature=TzLg6Xlb8WpgWZVFZRyTxqA4Mss%3D&from=3218412987","https://p9-sign.douyinpic.com/tos-cn-p-0015/0ed43b878b1c4e2f80b8408b6efa6daf_1660701991~noop.jpeg?x-expires=1660759200&x-signature=auHwtR0sNUMv6FR3EeuV14d91pA%3D&from=3218412987","https://p26-sign.douyinpic.com/tos-cn-p-0015/0ed43b878b1c4e2f80b8408b6efa6daf_1660701991~noop.jpeg?x-expires=1660759200&x-signature=ie6wjtcm7Swggr4I59wNDEG9G%2BU%3D&from=3218412987"]}},{"drift_info":null,"hotlist_param":"{\"version\":1}","room_count":0,"event_time":1660659080,"aweme_infos":null,"article_detail_count":0,"word_cover":{"uri":"tos-cn-p-0015/1994a2ba4cd742c683e6460d9ef22336","url_list":["https://p9-sign.douyinpic.com/tos-cn-p-0015/1994a2ba4cd742c683e6460d9ef22336~noop.jpeg?x-expires=1660759200&x-signature=ocCsdnoeqYR8BReZfHGCAmmytso%3D&from=3218412987","https://p3-sign.douyinpic.com/tos-cn-p-0015/1994a2ba4cd742c683e6460d9ef22336~noop.jpeg?x-expires=1660759200&x-signature=fLd3bh8fBsjATlncBH%2BYK5%2F79n8%3D&from=3218412987","https://p26-sign.douyinpic.com/tos-cn-p-0015/1994a2ba4cd742c683e6460d9ef22336~noop.jpeg?x-expires=1660759200&x-signature=ZPMYwBE801jc%2Ff%2FJg%2BOX1U8G9g0%3D&from=3218412987"]},"related_words":null,"word":"千里转运的小康康接受手术","label":0,"hot_value":6915921,"challenge_id":"","sentence_id":"772226","view_count":3052733,"sentence_tag":4004,"discuss_video_count":1,"position":48,"video_count":5,"group_id":"7132428892606518539","word_type":1,"word_sub_board":null},{"word":"怦然心动20岁第二季收官","label":3,"video_count":15,"can_extend_detail":false,"word_type":1,"related_words":null,"view_count":1160068,"sentence_tag":2003,"article_detail_count":0,"word_cover":{"uri":"tos-cn-p-0015/872e0b8b42304c6caca0bdd4fbec708c_1660658272","url_list":["https://p26-sign.douyinpic.com/tos-cn-p-0015/872e0b8b42304c6caca0bdd4fbec708c_1660658272~noop.jpeg?x-expires=1660759200&x-signature=SPfvM3AKGDVS3G%2Bq9Bqnirh9n8I%3D&from=3218412987","https://p9-sign.douyinpic.com/tos-cn-p-0015/872e0b8b42304c6caca0bdd4fbec708c_1660658272~noop.jpeg?x-expires=1660759200&x-signature=ZZ8NmjP9Lh5%2Bn2VQ4RKWzZb2lKo%3D&from=3218412987","https://p3-sign.douyinpic.com/tos-cn-p-0015/872e0b8b42304c6caca0bdd4fbec708c_1660658272~noop.jpeg?x-expires=1660759200&x-signature=rA0JaXMx7zHhk1CtInKvJCujX4s%3D&from=3218412987"]},"group_id":"7092391827333387528","hotlist_param":"{\"version\":1}","word_sub_board":null,"challenge_id":"","position":49,"discuss_video_count":1,"hot_value":6887611,"sentence_id":"772776","event_time":1660711553,"drift_info":null,"aweme_infos":null},{"word_cover":{"uri":"tos-cn-p-0015/777961f2dcf1484588c79c8deb71ab87_1660698916","url_list":["https://p26-sign.douyinpic.com/tos-cn-p-0015/777961f2dcf1484588c79c8deb71ab87_1660698916~noop.jpeg?x-expires=1660759200&x-signature=XT4ePthas4hYNMObBN2rPZcCXF0%3D&from=3218412987","https://p3-sign.douyinpic.com/tos-cn-p-0015/777961f2dcf1484588c79c8deb71ab87_1660698916~noop.jpeg?x-expires=1660759200&x-signature=WzNWg%2FZvqGKEtT9%2B1bGY9Urweb8%3D&from=3218412987","https://p9-sign.douyinpic.com/tos-cn-p-0015/777961f2dcf1484588c79c8deb71ab87_1660698916~noop.jpeg?x-expires=1660759200&x-signature=toXiVIsQuwKYl%2F64f2GniNO7vt0%3D&from=3218412987"]},"video_count":3,"word_type":1,"event_time":1660699225,"drift_info":null,"aweme_infos":null,"sentence_tag":4005,"label":3,"sentence_id":"772459","related_words":null,"word_sub_board":null,"article_detail_count":2,"word":"浙江新增本土阳性36例","hot_value":6861515,"challenge_id":"","position":50,"group_id":"7132381443196327199","view_count":2888678,"discuss_video_count":1,"hotlist_param":"{\"version\":1}"}],"active_time":"2022-08-17 20:53:43","share_info":{"share_url":"https://www.iesdouyin.com/share/billboard/?id=0","share_title":"我在看抖音热榜，发现最火的内容，赶快来看！","share_link_desc":"我在看抖音热榜，发现最火的内容，赶快来看！戳这里>>"},"trending_list":[{"word":"卡琳娜回应仲尼出轨","hot_value":0,"video_count":1,"word_type":3,"sentence_id":"773113","event_time":1660722655,"drift_info":null,"sentence_tag":2004,"discuss_video_count":1,"label":0,"hotlist_param":"{\"version\":1}","group_id":"7132382548843779359","related_words":null,"aweme_infos":null,"word_sub_board":null,"word_cover":{"uri":"tos-cn-p-0015/6dcb27d7d9b443c2888659a1b134b0fa","url_list":["https://p9-sign.douyinpic.com/tos-cn-p-0015/6dcb27d7d9b443c2888659a1b134b0fa~noop.jpeg?x-expires=1660759200&x-signature=4f1hVIcJ8XLVbREdmrtu52Baobw%3D&from=3218412987","https://p3-sign.douyinpic.com/tos-cn-p-0015/6dcb27d7d9b443c2888659a1b134b0fa~noop.jpeg?x-expires=1660759200&x-signature=KoxuAZPHZCEOrXBl2WWeRvIrpfg%3D&from=3218412987","https://p26-sign.douyinpic.com/tos-cn-p-0015/6dcb27d7d9b443c2888659a1b134b0fa~noop.jpeg?x-expires=1660759200&x-signature=Lrip0t3CtTI9qL29gd%2BqjfmxmZ8%3D&from=3218412987"]}},{"hot_value":0,"sentence_id":"772709","related_words":null,"drift_info":null,"sentence_tag":2012,"word_cover":{"uri":"tos-cn-p-0015/cb18610894304a01aae9f7dbe6ba1c0f","url_list":["https://p3-sign.douyinpic.com/tos-cn-p-0015/cb18610894304a01aae9f7dbe6ba1c0f~noop.jpeg?x-expires=1660759200&x-signature=Yf%2BK%2B76rIX0YZWgQCwU02x2Mcuw%3D&from=3218412987","https://p9-sign.douyinpic.com/tos-cn-p-0015/cb18610894304a01aae9f7dbe6ba1c0f~noop.jpeg?x-expires=1660759200&x-signature=9tZxLTiNqGpVjUFWTAOmviUqwvg%3D&from=3218412987","https://p26-sign.douyinpic.com/tos-cn-p-0015/cb18610894304a01aae9f7dbe6ba1c0f~noop.jpeg?x-expires=1660759200&x-signature=0YW2nKrQMcyb0pkU0V06e7q%2FpFY%3D&from=3218412987"]},"group_id":"6660235814074586381","discuss_video_count":1,"word_sub_board":null,"word":"爱情公寓诺澜近照","label":0,"word_type":3,"event_time":1660707083,"hotlist_param":"{\"version\":1}","aweme_infos":null,"video_count":2},{"group_id":"7131878931950490917","word":"李晨小杨哥梦幻联动","label":0,"sentence_id":"772569","related_words":null,"drift_info":null,"discuss_video_count":1,"hot_value":0,"word_cover":{"uri":"tos-cn-p-0015/8f7c8fb075d5471298aa018b8364c727","url_list":["https://p26-sign.douyinpic.com/tos-cn-p-0015/8f7c8fb075d5471298aa018b8364c727~noop.jpeg?x-expires=1660759200&x-signature=mvz93HyqDdL1%2BZCVBfsP51wdI0g%3D&from=3218412987","https://p3-sign.douyinpic.com/tos-cn-p-0015/8f7c8fb075d5471298aa018b8364c727~noop.jpeg?x-expires=1660759200&x-signature=dZfBBoMI%2F79Xf348O%2FDeZkNvv8s%3D&from=3218412987","https://p6-sign.douyinpic.com/tos-cn-p-0015/8f7c8fb075d5471298aa018b8364c727~noop.jpeg?x-expires=1660759200&x-signature=f%2BRla1onI%2F3yoT7tSuNhjlXGeOs%3D&from=3218412987"]},"word_type":3,"event_time":1660702839,"hotlist_param":"{\"version\":1}","word_sub_board":null,"video_count":2,"aweme_infos":null,"sentence_tag":2012},{"drift_info":null,"aweme_infos":null,"hot_value":0,"word_cover":{"uri":"tos-cn-p-0015/dee89038e9aa4d28982af3f44d6593e2_1660703145","url_list":["https://p26-sign.douyinpic.com/tos-cn-p-0015/dee89038e9aa4d28982af3f44d6593e2_1660703145~noop.jpeg?x-expires=1660759200&x-signature=RDbB0i0HyLWUBMTtWRwPYLvGjRI%3D&from=3218412987","https://p6-sign.douyinpic.com/tos-cn-p-0015/dee89038e9aa4d28982af3f44d6593e2_1660703145~noop.jpeg?x-expires=1660759200&x-signature=D0QVCDolkyQytX5rDzSulw%2BfDcc%3D&from=3218412987","https://p3-sign.douyinpic.com/tos-cn-p-0015/dee89038e9aa4d28982af3f44d6593e2_1660703145~noop.jpeg?x-expires=1660759200&x-signature=TZdHPWzs3nnBXGo0ZlHG%2B4FvxZk%3D&from=3218412987"]},"video_count":8,"related_words":null,"discuss_video_count":1,"word":"二十不惑2开播","sentence_id":"772619","event_time":1660705493,"sentence_tag":2002,"label":0,"group_id":"6872355197307753736","word_type":3,"hotlist_param":"{\"version\":1}","word_sub_board":null},{"video_count":2,"drift_info":null,"hot_value":0,"word_cover":{"url_list":["https://p9-sign.douyinpic.com/tos-cn-p-0015/24bd4c466a8b4d678a5a36c394acdfe5~noop.jpeg?x-expires=1660759200&x-signature=zquc4UCrJYrvapaK6U4TmRN4SVc%3D&from=3218412987","https://p6-sign.douyinpic.com/tos-cn-p-0015/24bd4c466a8b4d678a5a36c394acdfe5~noop.jpeg?x-expires=1660759200&x-signature=%2FGbvvXdMNs6fEFtFrL7zfMQwMKc%3D&from=3218412987","https://p26-sign.douyinpic.com/tos-cn-p-0015/24bd4c466a8b4d678a5a36c394acdfe5~noop.jpeg?x-expires=1660759200&x-signature=9A905REFFLH%2BWuScz9qsJPbjelw%3D&from=3218412987"],"uri":"tos-cn-p-0015/24bd4c466a8b4d678a5a36c394acdfe5"},"group_id":"7131706308629681440","hotlist_param":"{\"version\":1}","aweme_infos":null,"article_detail_count":0,"event_time":1660707743,"discuss_video_count":1,"word_sub_board":null,"word":"湖南多地人工增雨成功","label":0,"word_type":3,"sentence_id":"772693","related_words":null,"sentence_tag":4004}],"trending_desc":"实时上升热点","recommend_list":null}}
