{"data":{"word_list":[{"aweme_infos":null,"discuss_video_count":1,"article_detail_count":2,"word":"日媒：24日核污染水排海或取消","position":1,"word_type":1,"hotlist_param":"{\"version\":1}","sentence_tag":3002,"word_sub_board":null,"label":3,"video_count":7,"event_time":1692780780,"drift_info":null,"word_cover":{"url_list":["https://p3-sign.douyinpic.com/tos-cn-p-0015/ooxAthyzgXaBjJ4fN1yeACAMEdlzMcIzujhH4D~noop.jpeg?x-expires=1692849600&x-signature=A%2FBR0qze1Zf5utUe0pgst7VZ1rQ%3D&from=3218412987","https://p9-sign.douyinpic.com/tos-cn-p-0015/ooxAthyzgXaBjJ4fN1yeACAMEdlzMcIzujhH4D~noop.jpeg?x-expires=1692849600&x-signature=ZR%2B79c8jN4qtlGrQPOsIJuayzqo%3D&from=3218412987","https://p26-sign.douyinpic.com/tos-cn-p-0015/ooxAthyzgXaBjJ4fN1yeACAMEdlzMcIzujhH4D~noop.jpeg?x-expires=1692849600&x-signature=d%2FAKm0x%2BMMSmE7I9q%2Bj05NCqD8s%3D&from=3218412987"],"uri":"tos-cn-p-0015/ooxAthyzgXaBjJ4fN1yeACAMEdlzMcIzujhH4D"},"can_extend_detail":false,"view_count":68202595,"emo_label":0,"related_words":null,"hot_value":11294253,"group_id":"7269021456038008118","room_count":0,"sentence_id":"1371356"},{"word_cover":{"uri":"tos-cn-p-0015/okeL9k1c5fsDAri9AAgAq1dbraJgt8QnGcNBgd","url_list":["https://p3-sign.douyinpic.com/tos-cn-p-0015/okeL9k1c5fsDAri9AAgAq1dbraJgt8QnGcNBgd~noop.jpeg?x-expires=1692849600&x-signature=S%2FGEf6y8c6MHRrK38eyAM5bdycA%3D&from=3218412987","https://p6-sign.douyinpic.com/tos-cn-p-0015/okeL9k1c5fsDAri9AAgAq1dbraJgt8QnGcNBgd~noop.jpeg?x-expires=1692849600&x-signature=%2FMrOGON4%2BJ8Ly61fa%2BBGW2fn37I%3D&from=3218412987","https://p26-sign.douyinpic.com/tos-cn-p-0015/okeL9k1c5fsDAri9AAgAq1dbraJgt8QnGcNBgd~noop.jpeg?x-expires=1692849600&x-signature=aNB48iRkiDdHoXcx7m2ejocPPWA%3D&from=3218412987"]},"word_type":1,"hotlist_param":"{\"version\":1}","aweme_infos":null,"sentence_tag":3002,"hot_value":11194033,"position":2,"group_id":"7260541864008193332","event_time":1692802387,"related_words":null,"discuss_video_count":1,"word_sub_board":null,"label":3,"can_extend_detail":false,"sentence_id":"1371846","view_count":66041757,"word":"美国对日本核污水排海态度","drift_info":null,"article_detail_count":1,"video_count":2},{"label":3,"group_id":"7268164397251220792","sentence_id":"1371179","event_time":1692774795,"sentence_tag":3002,"word_sub_board":null,"hot_value":11185890,"related_words":null,"aweme_infos":null,"article_detail_count":1,"position":3,"hotlist_param":"{\"version\":1}","word":"中国是金砖国家第一大贸易伙伴","word_cover":{"uri":"tos-cn-p-0015/db339ef1844b4015834580833dcfbabf_1692774607","url_list":["https://p3-sign.douyinpic.com/tos-cn-p-0015/db339ef1844b4015834580833dcfbabf_1692774607~noop.jpeg?x-expires=1692849600&x-signature=fTw7FFHb%2B3Efy%2FW67li0US8gpis%3D&from=3218412987","https://p9-sign.douyinpic.com/tos-cn-p-0015/db339ef1844b4015834580833dcfbabf_1692774607~noop.jpeg?x-expires=1692849600&x-signature=rG%2BqZYoQ2xQkTlvhLvYlRg5Gquk%3D&from=3218412987","https://p26-sign.douyinpic.com/tos-cn-p-0015/db339ef1844b4015834580833dcfbabf_1692774607~noop.jpeg?x-expires=1692849600&x-signature=67eN%2FcMHKZP0vlg0aa7i4%2BoNKcg%3D&from=3218412987"]},"video_count":6,"can_extend_detail":false,"word_type":1,"view_count":64164546,"drift_info":null,"discuss_video_count":1},{"related_words":null,"drift_info":null,"sentence_tag":4004,"word_sub_board":null,"hot_value":11115768,"position":4,"word_type":1,"word_cover":{"uri":"tos-cn-i-0813c001/oUAxUNEgC9Af8hmyDoepNcNJAWzQACAIdAxyGk","url_list":["https://p26-sign.douyinpic.com/tos-cn-i-0813c001/oUAxUNEgC9Af8hmyDoepNcNJAWzQACAIdAxyGk~noop.jpeg?x-expires=1692849600&x-signature=QYttUjZi5KoALrc8ygU456bmYkA%3D&from=3218412987","https://p9-sign.douyinpic.com/tos-cn-i-0813c001/oUAxUNEgC9Af8hmyDoepNcNJAWzQACAIdAxyGk~noop.jpeg?x-expires=1692849600&x-signature=lJcEveGEwlm%2FTLxdr1RYTlwwki0%3D&from=3218412987","https://p3-sign.douyinpic.com/tos-cn-i-0813c001/oUAxUNEgC9Af8hmyDoepNcNJAWzQACAIdAxyGk~noop.jpeg?x-expires=1692849600&x-signature=lJodzdzVsoa9mHURIS4DrLfEBjc%3D&from=3218412987"]},"display_style":0,"hotlist_param":"{\"version\":1}","aweme_infos":null,"discuss_video_count":1,"article_detail_count":3,"word":"女孩回应26岁还被爸爸接下班","group_id":"7268893094875469092","sentence_id":"1370623","event_time":1692753446,"view_count":63000919,"label":3,"video_count":6,"can_extend_detail":false},{"emo_label":0,"label":3,"aweme_infos":null,"discuss_video_count":1,"event_time":1692786565,"view_count":57411110,"sentence_tag":22002,"word":"辽宁大连发生4.6级地震","hot_value":11094399,"word_type":1,"word_sub_board":null,"group_id":"7269032347139200267","sentence_id":"1371536","related_words":null,"can_extend_detail":false,"room_count":0,"drift_info":null,"hotlist_param":"{\"version\":1}","article_detail_count":0,"word_cover":{"uri":"tos-cn-p-0015/oUCDSBbDfAywJfgE8gC77CAye4QG82BbnR37vL","url_list":["https://p9-sign.douyinpic.com/tos-cn-p-0015/oUCDSBbDfAywJfgE8gC77CAye4QG82BbnR37vL~noop.jpeg?x-expires=1692849600&x-signature=zwsQ04F%2BQZMRIuDgSS7G%2FbDcNEs%3D&from=3218412987","https://p26-sign.douyinpic.com/tos-cn-p-0015/oUCDSBbDfAywJfgE8gC77CAye4QG82BbnR37vL~noop.jpeg?x-expires=1692849600&x-signature=qFSOWG35PWeHfRI%2FappVwISp0r4%3D&from=3218412987","https://p3-sign.douyinpic.com/tos-cn-p-0015/oUCDSBbDfAywJfgE8gC77CAye4QG82BbnR37vL~noop.jpeg?x-expires=1692849600&x-signature=zZ3J3ui1ls8SbWbhjG1eIBPh%2F60%3D&from=3218412987"]},"position":5,"video_count":4},{"sentence_tag":8000,"word_sub_board":null,"group_id":"7268131042467992869","can_extend_detail":false,"word_type":1,"view_count":61662370,"article_detail_count":0,"video_count":3,"event_time":1692767021,"aweme_infos":null,"word":"拉萨发现国家二级保护动物兔狲","hot_value":11072214,"word_cover":{"url_list":["https://p6-sign.douyinpic.com/tos-cn-p-0015/4cb2f88a70064379a66fe970cab18c07_1692766535~noop.jpeg?x-expires=1692849600&x-signature=H5evqcAWMAR%2BU67EZUnG%2BS81h3Y%3D&from=3218412987","https://p3-sign.douyinpic.com/tos-cn-p-0015/4cb2f88a70064379a66fe970cab18c07_1692766535~noop.jpeg?x-expires=1692849600&x-signature=Zr9FUUDvednxigwvFlBeIEorG9I%3D&from=3218412987","https://p26-sign.douyinpic.com/tos-cn-p-0015/4cb2f88a70064379a66fe970cab18c07_1692766535~noop.jpeg?x-expires=1692849600&x-signature=GtNI9NquXiHHcQH8kh7%2BN%2BpQNf4%3D&from=3218412987"],"uri":"tos-cn-p-0015/4cb2f88a70064379a66fe970cab18c07_1692766535"},"position":6,"sentence_id":"1370941","related_words":null,"drift_info":null,"hotlist_param":"{\"version\":1}","label":3,"discuss_video_count":1},{"sentence_id":"1371255","word_sub_board":null,"word_cover":{"uri":"tos-cn-p-0015/ooz0yEhIEAgymtcNBRfDjdXbtmMiYAAHzBaeAM","url_list":["https://p3-sign.douyinpic.com/tos-cn-p-0015/ooz0yEhIEAgymtcNBRfDjdXbtmMiYAAHzBaeAM~noop.jpeg?x-expires=1692849600&x-signature=wuzQxTdKfP7ZxNWYPWMOSbty85I%3D&from=3218412987","https://p9-sign.douyinpic.com/tos-cn-p-0015/ooz0yEhIEAgymtcNBRfDjdXbtmMiYAAHzBaeAM~noop.jpeg?x-expires=1692849600&x-signature=ESq%2FdT%2BPOR%2BUpd1G7%2F0IwXmfCBU%3D&from=3218412987","https://p26-sign.douyinpic.com/tos-cn-p-0015/ooz0yEhIEAgymtcNBRfDjdXbtmMiYAAHzBaeAM~noop.jpeg?x-expires=1692849600&x-signature=2vq7hCcKhx2J7gc8WJ8GYeSdTzE%3D&from=3218412987"]},"related_words":null,"drift_info":null,"discuss_video_count":1,"position":7,"video_count":9,"group_id":"6847304949244630279","can_extend_detail":false,"word_type":1,"view_count":54765140,"sentence_tag":5000,"word":"欧怒大战","label":5,"hot_value":10940529,"event_time":1692778062,"hotlist_param":"{\"version\":1}","aweme_infos":null,"article_detail_count":0},{"discuss_video_count":1,"article_detail_count":3,"hot_value":10473396,"position":8,"group_id":"7268275948691526973","related_words":null,"view_count":56759101,"sentence_tag":6000,"word":"印度月船3号探测器成功登月","label":3,"video_count":4,"can_extend_detail":false,"sentence_id":"1371735","aweme_infos":null,"hotlist_param":"{\"version\":1}","word_sub_board":null,"word_cover":{"uri":"tos-cn-p-75b2c0/oQ0i6DmnAJGCWN7ebsJLBCUAIclgdyQP6f7fiE","url_list":["https://p3-sign.douyinpic.com/tos-cn-p-75b2c0/oQ0i6DmnAJGCWN7ebsJLBCUAIclgdyQP6f7fiE~noop.jpeg?x-expires=1692849600&x-signature=48f4FfP5BSKbieuC%2BGQnojbxIpU%3D&from=3218412987","https://p26-sign.douyinpic.com/tos-cn-p-75b2c0/oQ0i6DmnAJGCWN7ebsJLBCUAIclgdyQP6f7fiE~noop.jpeg?x-expires=1692849600&x-signature=%2FQXwpYOnAY%2BP3Ze1T6yeZmx1%2Fqg%3D&from=3218412987","https://p9-sign.douyinpic.com/tos-cn-p-75b2c0/oQ0i6DmnAJGCWN7ebsJLBCUAIclgdyQP6f7fiE~noop.jpeg?x-expires=1692849600&x-signature=eoye%2BgOLjis69pVQulWrFCH9y3o%3D&from=3218412987"]},"word_type":1,"room_count":0,"event_time":1692794415,"drift_info":null},{"hotlist_param":"{\"version\":1}","aweme_infos":null,"label":3,"related_words":null,"sentence_id":"1369559","event_time":1692685323,"view_count":57907339,"sentence_tag":2010,"discuss_video_count":1,"word_sub_board":null,"word":"李嘉明再发声指责电视套娃收费","video_count":6,"article_detail_count":2,"group_id":"7269425831972377908","can_extend_detail":false,"position":9,"word_type":1,"drift_info":null,"hot_value":10292771,"word_cover":{"uri":"tos-cn-p-0015/owgSZhhkyANuOcMLAzB078gcfB1EDINe1Aw4kj","url_list":["https://p3-sign.douyinpic.com/tos-cn-p-0015/owgSZhhkyANuOcMLAzB078gcfB1EDINe1Aw4kj~noop.jpeg?x-expires=1692849600&x-signature=4OvPxPwKuw5RgcgU5KWSZsUAXeM%3D&from=3218412987","https://p6-sign.douyinpic.com/tos-cn-p-0015/owgSZhhkyANuOcMLAzB078gcfB1EDINe1Aw4kj~noop.jpeg?x-expires=1692849600&x-signature=3NDo0d1O%2Fy%2FIQrO27aB4HDvUzqU%3D&from=3218412987","https://p26-sign.douyinpic.com/tos-cn-p-0015/owgSZhhkyANuOcMLAzB078gcfB1EDINe1Aw4kj~noop.jpeg?x-expires=1692849600&x-signature=ngwc1qTb07DJHSMERcKpiI2bm2M%3D&from=3218412987"]}},{"related_words":null,"word_sub_board":null,"video_count":3,"word_cover":{"url_list":["https://p26-sign.douyinpic.com/tos-cn-p-0015/oUgIWDamkAPIRuzRAnBeH1S5eCMICQb9nA0FLk~noop.jpeg?x-expires=1692849600&x-signature=eBN4335DZXhAMZjlE%2B%2BlvKJjULM%3D&from=3218412987","https://p3-sign.douyinpic.com/tos-cn-p-0015/oUgIWDamkAPIRuzRAnBeH1S5eCMICQb9nA0FLk~noop.jpeg?x-expires=1692849600&x-signature=%2FWcGbWcQhX%2B7dQ4jSJzjtRcBe%2B0%3D&from=3218412987","https://p9-sign.douyinpic.com/tos-cn-p-0015/oUgIWDamkAPIRuzRAnBeH1S5eCMICQb9nA0FLk~noop.jpeg?x-expires=1692849600&x-signature=jX9Sn3i1bwvWxgN%2Bu1SpAlFg%2BeM%3D&from=3218412987"],"uri":"tos-cn-p-0015/oUgIWDamkAPIRuzRAnBeH1S5eCMICQb9nA0FLk"},"position":10,"can_extend_detail":false,"word_type":1,"hotlist_param":"{\"version\":1}","article_detail_count":0,"hot_value":9806173,"label":3,"group_id":"7269793384104957245","sentence_id":"1371141","event_time":1692772918,"drift_info":null,"aweme_infos":null,"sentence_tag":20005,"word":"这波色情诈骗让小狗背锅","display_style":0,"discuss_video_count":1,"view_count":55990650},{"article_detail_count":4,"hot_value":9378005,"group_id":"7268955897074046247","word_type":1,"word_sub_board":null,"word_cover":{"uri":"tos-cn-p-0015/oE9mzCKcyzADds6lBNfhg2zXAcAewOdIEntXCs","url_list":["https://p3-sign.douyinpic.com/tos-cn-p-0015/oE9mzCKcyzADds6lBNfhg2zXAcAewOdIEntXCs~noop.jpeg?x-expires=1692849600&x-signature=vZRBV2OlSjdZ%2FvwN6VnNY4o8NgU%3D&from=3218412987","https://p26-sign.douyinpic.com/tos-cn-p-0015/oE9mzCKcyzADds6lBNfhg2zXAcAewOdIEntXCs~noop.jpeg?x-expires=1692849600&x-signature=G7ErBD3GlJiEg434c%2F6eFqE%2F1Z0%3D&from=3218412987","https://p11-sign.douyinpic.com/tos-cn-p-0015/oE9mzCKcyzADds6lBNfhg2zXAcAewOdIEntXCs~noop.jpeg?x-expires=1692849600&x-signature=MYQS%2Bciu6%2Bk7UDw78q%2BR4L1Xyhs%3D&from=3218412987"]},"position":11,"drift_info":null,"aweme_infos":null,"discuss_video_count":1,"word":"民政局回应七夕直播仅12对领证","event_time":1692771554,"hotlist_param":"{\"version\":1}","sentence_id":"1371091","related_words":null,"view_count":53570669,"sentence_tag":4003,"label":0,"video_count":5,"can_extend_detail":false},{"word_cover":{"uri":"tos-cn-p-0015/oQKIgZcES6xlA7yhCfs7Aph7lzDANEAteBBnnD","url_list":["https://p3-sign.douyinpic.com/tos-cn-p-0015/oQKIgZcES6xlA7yhCfs7Aph7lzDANEAteBBnnD~noop.jpeg?x-expires=1692849600&x-signature=L3cTFkn470Rvd0XccugUygKYHVk%3D&from=3218412987","https://p26-sign.douyinpic.com/tos-cn-p-0015/oQKIgZcES6xlA7yhCfs7Aph7lzDANEAteBBnnD~noop.jpeg?x-expires=1692849600&x-signature=7DJwWJkMM0gEQgYSsI5IMhPBQ94%3D&from=3218412987","https://p9-sign.douyinpic.com/tos-cn-p-0015/oQKIgZcES6xlA7yhCfs7Aph7lzDANEAteBBnnD~noop.jpeg?x-expires=1692849600&x-signature=RZAHG7ROQUl8x4LmYJYRHA8qWn0%3D&from=3218412987"]},"position":12,"group_id":"7268941277369423140","view_count":50492364,"word":"1名在缅赌诈头目被押解回国","hot_value":9330918,"video_count":4,"can_extend_detail":false,"aweme_infos":null,"sentence_tag":4003,"word_sub_board":null,"event_time":1692767428,"discuss_video_count":1,"article_detail_count":3,"label":3,"word_type":1,"sentence_id":"1370958","related_words":null,"drift_info":null,"hotlist_param":"{\"version\":1}"},{"word_type":1,"sentence_id":"1371736","discuss_video_count":1,"word":"油价五连涨","label":0,"can_extend_detail":false,"aweme_infos":null,"position":13,"video_count":4,"view_count":45383618,"word_sub_board":null,"article_detail_count":5,"hot_value":9206252,"group_id":"6575636310839547143","related_words":null,"hotlist_param":"{\"version\":1}","sentence_tag":7000,"word_cover":{"uri":"tos-cn-p-0015/ocQfADZ8JHBsvWdLCf8DAwnFByA7cy8QIkboGf","url_list":["https://p9-sign.douyinpic.com/tos-cn-p-0015/ocQfADZ8JHBsvWdLCf8DAwnFByA7cy8QIkboGf~noop.jpeg?x-expires=1692849600&x-signature=4b5k%2FTAAhOWWuUmsHEXEOTEzPmY%3D&from=3218412987","https://p6-sign.douyinpic.com/tos-cn-p-0015/ocQfADZ8JHBsvWdLCf8DAwnFByA7cy8QIkboGf~noop.jpeg?x-expires=1692849600&x-signature=V%2F1JLRx4UMmsEeKWndJHAejtB%2FI%3D&from=3218412987","https://p26-sign.douyinpic.com/tos-cn-p-0015/ocQfADZ8JHBsvWdLCf8DAwnFByA7cy8QIkboGf~noop.jpeg?x-expires=1692849600&x-signature=nzTJjsxzyP4QTKPX6hEiLbY1fnU%3D&from=3218412987"]},"event_time":1692794457,"drift_info":null},{"position":14,"can_extend_detail":false,"event_time":1692795894,"view_count":47232759,"aweme_infos":null,"article_detail_count":0,"sentence_id":"1371755","related_words":null,"drift_info":null,"word_sub_board":null,"hot_value":8982447,"word_cover":{"uri":"tos-cn-p-0015/owZQgi5IeQK2ANk0Q8duAlDblnq5bpAE9EBrfC","url_list":["https://p26-sign.douyinpic.com/tos-cn-p-0015/owZQgi5IeQK2ANk0Q8duAlDblnq5bpAE9EBrfC~noop.jpeg?x-expires=1692849600&x-signature=9LT8z0y6gUuYb5r6vfBuX3Bb8%2BU%3D&from=3218412987","https://p3-sign.douyinpic.com/tos-cn-p-0015/owZQgi5IeQK2ANk0Q8duAlDblnq5bpAE9EBrfC~noop.jpeg?x-expires=1692849600&x-signature=Dm2oFO369FnpgP1SFeWYWvof%2FRY%3D&from=3218412987","https://p11-sign.douyinpic.com/tos-cn-p-0015/owZQgi5IeQK2ANk0Q8duAlDblnq5bpAE9EBrfC~noop.jpeg?x-expires=1692849600&x-signature=uDTPoRg2%2F4rLNErpawqZmdxTVVg%3D&from=3218412987"]},"video_count":1,"word_type":1,"hotlist_param":"{\"version\":1}","sentence_tag":2001,"word":"张艺兴孤注一掷30亿福利","label":0,"group_id":"7269563763639981324","discuss_video_count":1},{"position":15,"can_extend_detail":false,"word_type":1,"drift_info":null,"aweme_infos":null,"sentence_tag":4004,"word_sub_board":null,"label":3,"discuss_video_count":1,"group_id":"7269787781826696463","video_count":3,"sentence_id":"1371061","event_time":1692770516,"related_words":null,"view_count":42149131,"display_style":0,"word_cover":{"uri":"tos-cn-p-0015/oIXINQfOgA7cAkZo9ebyXknBA25DsDAgwZF4BK","url_list":["https://p6-sign.douyinpic.com/tos-cn-p-0015/oIXINQfOgA7cAkZo9ebyXknBA25DsDAgwZF4BK~noop.jpeg?x-expires=1692849600&x-signature=6Dw6yTt3IQ0RpkgIDWBOxcw6df0%3D&from=3218412987","https://p3-sign.douyinpic.com/tos-cn-p-0015/oIXINQfOgA7cAkZo9ebyXknBA25DsDAgwZF4BK~noop.jpeg?x-expires=1692849600&x-signature=ovGL0fsn2V3KcCa4IaQRfj%2F%2BLvk%3D&from=3218412987","https://p26-sign.douyinpic.com/tos-cn-p-0015/oIXINQfOgA7cAkZo9ebyXknBA25DsDAgwZF4BK~noop.jpeg?x-expires=1692849600&x-signature=3qwF5tIpv1ZKB%2Bw12miwKNmVv%2Bk%3D&from=3218412987"]},"hot_value":8845475,"hotlist_param":"{\"version\":1}","article_detail_count":0,"word":"董宇辉称没想过取代俞敏洪"},{"hot_value":8811538,"word_cover":{"uri":"tos-cn-p-0015/o4PyBb14nAjkeBfAIlD0d5Eu5BNICyagMQ96LA","url_list":["https://p3-sign.douyinpic.com/tos-cn-p-0015/o4PyBb14nAjkeBfAIlD0d5Eu5BNICyagMQ96LA~noop.jpeg?x-expires=1692849600&x-signature=cdH5LlnHwLz%2BLnYPWpFrZVC6hZg%3D&from=3218412987","https://p26-sign.douyinpic.com/tos-cn-p-0015/o4PyBb14nAjkeBfAIlD0d5Eu5BNICyagMQ96LA~noop.jpeg?x-expires=1692849600&x-signature=8h7X75liRF2eTTxzeKNKcy6vbpg%3D&from=3218412987","https://p9-sign.douyinpic.com/tos-cn-p-0015/o4PyBb14nAjkeBfAIlD0d5Eu5BNICyagMQ96LA~noop.jpeg?x-expires=1692849600&x-signature=N1734Ci3rNZKfb7DTQi3YjIr60M%3D&from=3218412987"]},"position":16,"group_id":"7269045097923384639","can_extend_detail":false,"event_time":1692790642,"view_count":46938371,"hotlist_param":"{\"version\":1}","article_detail_count":0,"label":0,"word_type":1,"sentence_id":"1371632","aweme_infos":null,"word":"冯绍峰提到了知否","word_sub_board":null,"video_count":1,"related_words":null,"drift_info":null,"sentence_tag":2002,"discuss_video_count":1},{"word":"曾号称喝核污水的日官员怎么样了","hot_value":8786450,"word_type":1,"sentence_id":"1371514","view_count":43685733,"label":0,"position":17,"video_count":1,"can_extend_detail":false,"aweme_infos":null,"discuss_video_count":1,"word_sub_board":null,"event_time":1692785661,"related_words":null,"hotlist_param":"{\"version\":1}","word_cover":{"uri":"tos-cn-p-0015/o0r6IDIknnAqzQckfc8fA9kCPA9gGBc5QbbPlD","url_list":["https://p3-sign.douyinpic.com/tos-cn-p-0015/o0r6IDIknnAqzQckfc8fA9kCPA9gGBc5QbbPlD~noop.jpeg?x-expires=1692849600&x-signature=QpxpoFHNJJ3KG6B7qa6f1GRJy0o%3D&from=3218412987","https://p26-sign.douyinpic.com/tos-cn-p-0015/o0r6IDIknnAqzQckfc8fA9kCPA9gGBc5QbbPlD~noop.jpeg?x-expires=1692849600&x-signature=e9Mmqn0M1YlTa8vl1OVbrkmY3TE%3D&from=3218412987","https://p6-sign.douyinpic.com/tos-cn-p-0015/o0r6IDIknnAqzQckfc8fA9kCPA9gGBc5QbbPlD~noop.jpeg?x-expires=1692849600&x-signature=k%2Fmecu%2FRO8qpzPqQXOutusOsDI8%3D&from=3218412987"]},"group_id":"7270245030697162023","drift_info":null,"sentence_tag":3002,"article_detail_count":1},{"label":0,"hot_value":8729042,"video_count":3,"sentence_id":"1370174","related_words":null,"view_count":43714283,"aweme_infos":null,"sentence_tag":20002,"can_extend_detail":false,"word_cover":{"uri":"tos-cn-p-0015/oAA4gjQgDyA8MDIgfY9an5bveInJABogILvk4k","url_list":["https://p3-sign.douyinpic.com/tos-cn-p-0015/oAA4gjQgDyA8MDIgfY9an5bveInJABogILvk4k~noop.jpeg?x-expires=1692849600&x-signature=UmSvu07AsIWluzm8bW0yPG8Tuow%3D&from=3218412987","https://p26-sign.douyinpic.com/tos-cn-p-0015/oAA4gjQgDyA8MDIgfY9an5bveInJABogILvk4k~noop.jpeg?x-expires=1692849600&x-signature=bescalqSNG3eGkTZy2ytKDGxvM4%3D&from=3218412987","https://p9-sign.douyinpic.com/tos-cn-p-0015/oAA4gjQgDyA8MDIgfY9an5bveInJABogILvk4k~noop.jpeg?x-expires=1692849600&x-signature=mAzkH6S0Y0i7pLo%2BrJZ3PB2lbek%3D&from=3218412987"]},"word_type":1,"event_time":1692705632,"hotlist_param":"{\"version\":1}","word":"小武和小雨订婚了","position":18,"group_id":"7265687926950909225","drift_info":null,"discuss_video_count":1,"word_sub_board":null,"article_detail_count":0},{"group_id":"7269896447473964323","sentence_id":"1371424","hotlist_param":"{\"version\":1}","discuss_video_count":1,"can_extend_detail":false,"word_type":1,"view_count":39683935,"aweme_infos":null,"word_cover":{"url_list":["https://p11-sign.douyinpic.com/tos-cn-p-0015/oIX6ywBeEDFMCXmAczkAlnMB5I5tNewbgAt8X9~noop.jpeg?x-expires=1692849600&x-signature=eJjSphffgaODOxiSmQ6pYlqNbpo%3D&from=3218412987","https://p3-sign.douyinpic.com/tos-cn-p-0015/oIX6ywBeEDFMCXmAczkAlnMB5I5tNewbgAt8X9~noop.jpeg?x-expires=1692849600&x-signature=fpCFvLoMqQI75RTShfbWJTRGXtE%3D&from=3218412987","https://p26-sign.douyinpic.com/tos-cn-p-0015/oIX6ywBeEDFMCXmAczkAlnMB5I5tNewbgAt8X9~noop.jpeg?x-expires=1692849600&x-signature=%2FgwIMCWQVVo4Be0go1OFFzx3rPw%3D&from=3218412987"],"uri":"tos-cn-p-0015/oIX6ywBeEDFMCXmAczkAlnMB5I5tNewbgAt8X9"},"video_count":8,"event_time":1692782549,"drift_info":null,"article_detail_count":2,"word":"清华专家谈日本核污水排海","label":0,"hot_value":8579698,"position":19,"related_words":null,"sentence_tag":3002,"word_sub_board":null},{"word":"媒体评妻子炫富式举报丈夫","related_words":null,"article_detail_count":5,"view_count":39750151,"hotlist_param":"{\"version\":1}","sentence_tag":4003,"word_sub_board":null,"hot_value":8440229,"video_count":5,"sentence_id":"1371313","drift_info":null,"discuss_video_count":1,"position":20,"group_id":"7269849428629607714","word_type":1,"event_time":1692779784,"aweme_infos":null,"label":3,"word_cover":{"url_list":["https://p3-sign.douyinpic.com/tos-cn-p-0015/882b4346386b4fd5bd64e91eb004110f_1692774749~noop.jpeg?x-expires=1692849600&x-signature=rNA4M3US7fjsHJ%2FurliUZcFGFGE%3D&from=3218412987","https://p26-sign.douyinpic.com/tos-cn-p-0015/882b4346386b4fd5bd64e91eb004110f_1692774749~noop.jpeg?x-expires=1692849600&x-signature=1sB%2BVNdMSyO1Y8hbwEisGQEk6rc%3D&from=3218412987","https://p9-sign.douyinpic.com/tos-cn-p-0015/882b4346386b4fd5bd64e91eb004110f_1692774749~noop.jpeg?x-expires=1692849600&x-signature=Q6SSKTxSGq5OFW78LRnbc7xV%2FkM%3D&from=3218412987"],"uri":"tos-cn-p-0015/882b4346386b4fd5bd64e91eb004110f_1692774749"},"can_extend_detail":false},{"word":"虞书欣不规则辣妹裙造型","label":0,"group_id":"7268139186807838009","related_words":null,"drift_info":null,"discuss_video_count":1,"word_cover":{"uri":"tos-cn-p-0015/oAtMlGGAABBhMVgoB3zuDkIx5EzeKn9tZfQArn","url_list":["https://p26-sign.douyinpic.com/tos-cn-p-0015/oAtMlGGAABBhMVgoB3zuDkIx5EzeKn9tZfQArn~noop.jpeg?x-expires=1692849600&x-signature=zBpAl1YmUeyCKHgfgEzZkOfiBQ4%3D&from=3218412987","https://p3-sign.douyinpic.com/tos-cn-p-0015/oAtMlGGAABBhMVgoB3zuDkIx5EzeKn9tZfQArn~noop.jpeg?x-expires=1692849600&x-signature=SQC8urwGJGcY%2Ft4pWzeIDMxGJn4%3D&from=3218412987","https://p9-sign.douyinpic.com/tos-cn-p-0015/oAtMlGGAABBhMVgoB3zuDkIx5EzeKn9tZfQArn~noop.jpeg?x-expires=1692849600&x-signature=UMIayVtYmeE78Y3Do%2B7F6YcmZtU%3D&from=3218412987"]},"position":21,"can_extend_detail":false,"word_type":1,"view_count":43739782,"hot_value":8418671,"video_count":1,"sentence_id":"1371123","event_time":1692772313,"hotlist_param":"{\"version\":1}","word_sub_board":null,"aweme_infos":null,"sentence_tag":2008,"article_detail_count":0},{"related_words":null,"drift_info":null,"word_cover":{"uri":"tos-cn-p-0015/ogpAaNtl5gvezaFIBDDhALBNuAcfEpTJyn1Htr","url_list":["https://p26-sign.douyinpic.com/tos-cn-p-0015/ogpAaNtl5gvezaFIBDDhALBNuAcfEpTJyn1Htr~noop.jpeg?x-expires=1692849600&x-signature=lYgmIjUMUyIT8sr5mNQoJ32ym4E%3D&from=3218412987","https://p3-sign.douyinpic.com/tos-cn-p-0015/ogpAaNtl5gvezaFIBDDhALBNuAcfEpTJyn1Htr~noop.jpeg?x-expires=1692849600&x-signature=IeGI92gS%2FIFO8EAnOhfUBe2B0rM%3D&from=3218412987","https://p6-sign.douyinpic.com/tos-cn-p-0015/ogpAaNtl5gvezaFIBDDhALBNuAcfEpTJyn1Htr~noop.jpeg?x-expires=1692849600&x-signature=OfZf22Yy0N4XsltFoT51UKp8wBw%3D&from=3218412987"]},"video_count":1,"hotlist_param":"{\"version\":1}","discuss_video_count":1,"word_sub_board":null,"hot_value":8405050,"can_extend_detail":false,"word_type":1,"sentence_id":"1371416","event_time":1692782271,"aweme_infos":null,"label":3,"group_id":"7269870405472572712","view_count":36461224,"sentence_tag":2012,"article_detail_count":0,"word":"成毅被粉丝提醒踩裤子了","position":22},{"word_cover":{"uri":"tos-cn-p-0015/6d482874a384415a96179ec5a5eb481c_1692712762","url_list":["https://p26-sign.douyinpic.com/tos-cn-p-0015/6d482874a384415a96179ec5a5eb481c_1692712762~noop.jpeg?x-expires=1692849600&x-signature=GTAf1JsZgzaEsnGLbHLSzSqvwX0%3D&from=3218412987","https://p3-sign.douyinpic.com/tos-cn-p-0015/6d482874a384415a96179ec5a5eb481c_1692712762~noop.jpeg?x-expires=1692849600&x-signature=SB5WfKoSPMV2mylIb9DuFqlET70%3D&from=3218412987","https://p9-sign.douyinpic.com/tos-cn-p-0015/6d482874a384415a96179ec5a5eb481c_1692712762~noop.jpeg?x-expires=1692849600&x-signature=U3MEKz6VJxPbfG%2BHLHtabDMPebI%3D&from=3218412987"]},"position":23,"group_id":"7268539609389258003","sentence_id":"1370768","view_count":37940500,"drift_info":null,"article_detail_count":5,"video_count":33,"word_type":1,"sentence_tag":20005,"word":"核污水排海意味着什么","label":0,"can_extend_detail":false,"related_words":null,"hotlist_param":"{\"version\":1}","discuss_video_count":1,"hot_value":8393415,"event_time":1692758893,"aweme_infos":null,"word_sub_board":null,"emo_label":0},{"related_words":null,"view_count":34421065,"hotlist_param":"{\"version\":1}","word_cover":{"uri":"tos-cn-p-0015/oQIeF9Bk55K1p8vPAS3nPgDANfAbAQX2dQGaDW","url_list":["https://p3-sign.douyinpic.com/tos-cn-p-0015/oQIeF9Bk55K1p8vPAS3nPgDANfAbAQX2dQGaDW~noop.jpeg?x-expires=1692849600&x-signature=d4t3irxAmAmKhzzKdRwp%2FbK%2B0uY%3D&from=3218412987","https://p6-sign.douyinpic.com/tos-cn-p-0015/oQIeF9Bk55K1p8vPAS3nPgDANfAbAQX2dQGaDW~noop.jpeg?x-expires=1692849600&x-signature=44rRdIhsXWSmQy3%2FQqWrp1sgNKs%3D&from=3218412987","https://p26-sign.douyinpic.com/tos-cn-p-0015/oQIeF9Bk55K1p8vPAS3nPgDANfAbAQX2dQGaDW~noop.jpeg?x-expires=1692849600&x-signature=ltfeel41j6%2Fd0Rkp%2BoLQ231ezNw%3D&from=3218412987"]},"position":24,"can_extend_detail":false,"word_type":1,"sentence_id":"1371129","event_time":1692772473,"article_detail_count":3,"label":3,"group_id":"7270394921646675259","discuss_video_count":1,"word_sub_board":null,"word":"香港工联会抗议日本核污水排海","drift_info":null,"aweme_infos":null,"sentence_tag":3002,"hot_value":8383528,"video_count":4},{"hot_value":8371496,"video_count":1,"discuss_video_count":1,"word_cover":{"url_list":["https://p26-sign.douyinpic.com/tos-cn-p-0015/oQhZICeAEAANRIXlByOg0uVUDBfiSkczsl7GgE~noop.jpeg?x-expires=1692849600&x-signature=%2Bg1Psik5%2FWCAqXfvUznt%2FdlewAM%3D&from=3218412987","https://p3-sign.douyinpic.com/tos-cn-p-0015/oQhZICeAEAANRIXlByOg0uVUDBfiSkczsl7GgE~noop.jpeg?x-expires=1692849600&x-signature=2cc3%2BhiJEDbB4oYa4RiOf34wbbE%3D&from=3218412987","https://p9-sign.douyinpic.com/tos-cn-p-0015/oQhZICeAEAANRIXlByOg0uVUDBfiSkczsl7GgE~noop.jpeg?x-expires=1692849600&x-signature=ChczZ3Z2mACr0okl61%2BOkyNIUxQ%3D&from=3218412987"],"uri":"tos-cn-p-0015/oQhZICeAEAANRIXlByOg0uVUDBfiSkczsl7GgE"},"can_extend_detail":false,"event_time":1692782707,"sentence_tag":3002,"article_detail_count":1,"position":25,"group_id":"7269017155335738663","sentence_id":"1371432","aweme_infos":null,"word":"普京：乌当局不把士兵当人看","label":0,"word_type":1,"related_words":null,"view_count":35670381,"drift_info":null,"hotlist_param":"{\"version\":1}","word_sub_board":null},{"group_id":"7270161528983328059","can_extend_detail":false,"sentence_id":"1370567","drift_info":null,"aweme_infos":null,"hot_value":8331032,"video_count":16,"word_type":1,"related_words":null,"discuss_video_count":1,"article_detail_count":5,"word_cover":{"uri":"tos-cn-p-0015/okIulkwAKBVeSg9xo2QA78DANUnNg5CKfbmw3N","url_list":["https://p3-sign.douyinpic.com/tos-cn-p-0015/okIulkwAKBVeSg9xo2QA78DANUnNg5CKfbmw3N~noop.jpeg?x-expires=1692849600&x-signature=FVcRU0lPEo9ehaLZ1FLSHCL%2BWlI%3D&from=3218412987","https://p26-sign.douyinpic.com/tos-cn-p-0015/okIulkwAKBVeSg9xo2QA78DANUnNg5CKfbmw3N~noop.jpeg?x-expires=1692849600&x-signature=UttP5J%2B5Fo2%2FiLmkCi%2BPX9MzM%2BA%3D&from=3218412987","https://p9-sign.douyinpic.com/tos-cn-p-0015/okIulkwAKBVeSg9xo2QA78DANUnNg5CKfbmw3N~noop.jpeg?x-expires=1692849600&x-signature=t%2BwGzbmG%2Bf1GmH415ZGLING%2BGB4%3D&from=3218412987"]},"label":0,"position":26,"hotlist_param":"{\"version\":1}","sentence_tag":3002,"emo_label":0,"word":"东电公布第一批核污水排放计划","view_count":30215242,"word_sub_board":null,"event_time":1692751251},{"room_count":0,"event_time":1692787946,"related_words":null,"hotlist_param":"{\"version\":1}","group_id":"7268238276103689533","sentence_tag":4003,"discuss_video_count":1,"word_sub_board":null,"word":"万名特种兵夜爬武功山","label":3,"hot_value":8295650,"video_count":1,"sentence_id":"1371562","view_count":30046321,"aweme_infos":null,"article_detail_count":0,"word_cover":{"uri":"webcast-cover/7270147724392172322","url_list":["https://p26-sign.douyinpic.com/obj/webcast-cover/7270147724392172322?x-expires=1692849600&x-signature=x0h4fvztT%2Btd0mSzo2WYA7CxrJQ%3D&from=3218412987","https://p3-sign.douyinpic.com/obj/webcast-cover/7270147724392172322?x-expires=1692849600&x-signature=g3UCVC14TWKo2S3hpUPfzKx7VAU%3D&from=3218412987","https://p6-sign.douyinpic.com/obj/webcast-cover/7270147724392172322?x-expires=1692849600&x-signature=0HCc2%2BMiXaYLif81WADnsJsuu2s%3D&from=3218412987"]},"position":27,"can_extend_detail":false,"word_type":1,"drift_info":null},{"sentence_tag":3002,"article_detail_count":2,"label":0,"can_extend_detail":false,"view_count":28006517,"hotlist_param":"{\"version\":1}","sentence_id":"1370698","word":"韩国回应日本核污水排海","hot_value":8270080,"position":28,"word_type":1,"video_count":4,"event_time":1692755676,"discuss_video_count":1,"word_sub_board":null,"aweme_infos":null,"word_cover":{"uri":"tos-cn-p-0015/3124d873ac0a4c66bed7e500e46afe81_1692709929","url_list":["https://p6-sign.douyinpic.com/tos-cn-p-0015/3124d873ac0a4c66bed7e500e46afe81_1692709929~noop.jpeg?x-expires=1692849600&x-signature=aNLefNuNuU6jBWZmtU9pvBjaaGs%3D&from=3218412987","https://p11-sign.douyinpic.com/tos-cn-p-0015/3124d873ac0a4c66bed7e500e46afe81_1692709929~noop.jpeg?x-expires=1692849600&x-signature=TgVwhe4ZqabMLOVVOR1i4UjpJ8g%3D&from=3218412987","https://p3-sign.douyinpic.com/tos-cn-p-0015/3124d873ac0a4c66bed7e500e46afe81_1692709929~noop.jpeg?x-expires=1692849600&x-signature=b8SOq51JrcAmSwAb%2FLEO0K8IeMw%3D&from=3218412987"]},"group_id":"7187731792937047330","related_words":null,"drift_info":null},{"hot_value":8253602,"group_id":"7269043394332153127","hotlist_param":"{\"version\":1}","word_sub_board":null,"article_detail_count":0,"aweme_infos":null,"position":29,"can_extend_detail":false,"word_type":1,"sentence_id":"1371724","drift_info":null,"video_count":2,"discuss_video_count":1,"view_count":25678908,"sentence_tag":6000,"word":"日本团队称外星人将回复地球来信","label":0,"word_cover":{"uri":"tos-cn-p-0015/oYgyYPQohNZweklzfYfHVAfGOldfTfdPVJcAAI","url_list":["https://p3-sign.douyinpic.com/tos-cn-p-0015/oYgyYPQohNZweklzfYfHVAfGOldfTfdPVJcAAI~noop.jpeg?x-expires=1692849600&x-signature=BWPidLtDBRJhoqkUDhcnboA5ndQ%3D&from=3218412987","https://p26-sign.douyinpic.com/tos-cn-p-0015/oYgyYPQohNZweklzfYfHVAfGOldfTfdPVJcAAI~noop.jpeg?x-expires=1692849600&x-signature=HeOotYrqnalTo5vOgdGd3jGvPZw%3D&from=3218412987","https://p6-sign.douyinpic.com/tos-cn-p-0015/oYgyYPQohNZweklzfYfHVAfGOldfTfdPVJcAAI~noop.jpeg?x-expires=1692849600&x-signature=%2BqK0yKCYTIhTFCH8pMXrD8T%2BzJ0%3D&from=3218412987"]},"event_time":1692793874,"related_words":null},{"word":"赵露思丝滑混入小孩圈","hot_value":8207387,"video_count":4,"sentence_id":"1371422","event_time":1692782449,"word_sub_board":null,"article_detail_count":0,"drift_info":null,"word_cover":{"uri":"tos-cn-p-0015/oE5A8BDbdfnP99gN7gqq8cWAbzCFukgAfmQbnN","url_list":["https://p26-sign.douyinpic.com/tos-cn-p-0015/oE5A8BDbdfnP99gN7gqq8cWAbzCFukgAfmQbnN~noop.jpeg?x-expires=1692849600&x-signature=hA7e5sQQb22%2BLWpp2RwDwCrvMuI%3D&from=3218412987","https://p3-sign.douyinpic.com/tos-cn-p-0015/oE5A8BDbdfnP99gN7gqq8cWAbzCFukgAfmQbnN~noop.jpeg?x-expires=1692849600&x-signature=2bmxzvtnjfwvTaJLckDRLUR1epA%3D&from=3218412987","https://p9-sign.douyinpic.com/tos-cn-p-0015/oE5A8BDbdfnP99gN7gqq8cWAbzCFukgAfmQbnN~noop.jpeg?x-expires=1692849600&x-signature=0V5DHKlt3%2BVGNxiwHmwz0YsU674%3D&from=3218412987"]},"position":30,"can_extend_detail":false,"word_type":1,"aweme_infos":null,"label":0,"group_id":"7268195441883436348","related_words":null,"view_count":25598084,"hotlist_param":"{\"version\":1}","sentence_tag":2003,"discuss_video_count":1},{"group_id":"7269009604859909388","event_time":1692781506,"related_words":null,"drift_info":null,"word_sub_board":null,"word_cover":{"url_list":["https://p26-sign.douyinpic.com/tos-cn-p-0015/107d00c66d6b41c0aa3f834ddf78afb2_1692769752~noop.jpeg?x-expires=1692849600&x-signature=BZ%2FQwy0VmNemMZHbAd%2FkjhB7Pgo%3D&from=3218412987","https://p3-sign.douyinpic.com/tos-cn-p-0015/107d00c66d6b41c0aa3f834ddf78afb2_1692769752~noop.jpeg?x-expires=1692849600&x-signature=03vqt1nF96%2Bw8rq83KTlIryDbVE%3D&from=3218412987","https://p6-sign.douyinpic.com/tos-cn-p-0015/107d00c66d6b41c0aa3f834ddf78afb2_1692769752~noop.jpeg?x-expires=1692849600&x-signature=QNEpJIZfpwvYov6P5YrstnMpac4%3D&from=3218412987"],"uri":"tos-cn-p-0015/107d00c66d6b41c0aa3f834ddf78afb2_1692769752"},"can_extend_detail":false,"word_type":1,"sentence_id":"1371386","view_count":24539453,"aweme_infos":null,"sentence_tag":2012,"label":3,"video_count":3,"article_detail_count":0,"word":"毛晓彤whatever舞","hot_value":8195644,"position":31,"hotlist_param":"{\"version\":1}","discuss_video_count":1},{"word":"日本专家：核污水排海后患无穷","word_cover":{"url_list":["https://p3-sign.douyinpic.com/tos-cn-p-0015/o84AELfcyEzxtLBARkygt9hVylIBeLxAC9OraB~noop.jpeg?x-expires=1692849600&x-signature=7QkpsO0J9Ks%2FxmQK2m4QjQu3OTI%3D&from=3218412987","https://p11-sign.douyinpic.com/tos-cn-p-0015/o84AELfcyEzxtLBARkygt9hVylIBeLxAC9OraB~noop.jpeg?x-expires=1692849600&x-signature=pk7%2B%2FwSMoikp3V0M88FDSHt9EOA%3D&from=3218412987","https://p26-sign.douyinpic.com/tos-cn-p-0015/o84AELfcyEzxtLBARkygt9hVylIBeLxAC9OraB~noop.jpeg?x-expires=1692849600&x-signature=Uv%2BZQIAdwdgzssWT5KIZzBrnXQ4%3D&from=3218412987"],"uri":"tos-cn-p-0015/o84AELfcyEzxtLBARkygt9hVylIBeLxAC9OraB"},"word_type":1,"sentence_id":"1370729","event_time":1692757479,"view_count":22865014,"article_detail_count":5,"label":0,"video_count":11,"group_id":"7268097189401302328","related_words":null,"aweme_infos":null,"discuss_video_count":1,"hot_value":8192380,"drift_info":null,"hotlist_param":"{\"version\":1}","word_sub_board":null,"position":32,"can_extend_detail":false,"sentence_tag":3002},{"video_count":4,"related_words":null,"drift_info":null,"hotlist_param":"{\"version\":1}","word_sub_board":null,"label":0,"hot_value":8181843,"position":33,"group_id":"7269719991338718479","sentence_id":"1370565","event_time":1692751195,"view_count":21625062,"aweme_infos":null,"discuss_video_count":1,"article_detail_count":0,"word":"老人误将2万元汉服当垃圾扔掉","word_cover":{"url_list":["https://p3-sign.douyinpic.com/tos-cn-p-0015/ocaZEjeCIKDcmfgkABnAIW5M9Wkg1BzA9NDdb7~noop.jpeg?x-expires=1692849600&x-signature=C5C6n3P18ogGrv4qkQAfNenUVbU%3D&from=3218412987","https://p26-sign.douyinpic.com/tos-cn-p-0015/ocaZEjeCIKDcmfgkABnAIW5M9Wkg1BzA9NDdb7~noop.jpeg?x-expires=1692849600&x-signature=jO0GeE4hiPMNdDxmN7G5vANLX44%3D&from=3218412987","https://p6-sign.douyinpic.com/tos-cn-p-0015/ocaZEjeCIKDcmfgkABnAIW5M9Wkg1BzA9NDdb7~noop.jpeg?x-expires=1692849600&x-signature=bNw8mC0PcMprN1tTTgQuGBFW8Po%3D&from=3218412987"],"uri":"tos-cn-p-0015/ocaZEjeCIKDcmfgkABnAIW5M9Wkg1BzA9NDdb7"},"can_extend_detail":false,"word_type":1,"sentence_tag":4004},{"word_sub_board":null,"article_detail_count":6,"position":34,"video_count":3,"group_id":"7270036842959181113","event_time":1692755125,"related_words":null,"view_count":20011784,"word":"初二女生夺100米世界级冠军","hotlist_param":"{\"version\":1}","aweme_infos":null,"discuss_video_count":1,"label":0,"hot_value":8178655,"word_cover":{"uri":"tos-cn-p-0015/oQP2RAbED5QCyx9HAkg8IjeDdnS3AkKenHAWBb","url_list":["https://p3-sign.douyinpic.com/tos-cn-p-0015/oQP2RAbED5QCyx9HAkg8IjeDdnS3AkKenHAWBb~noop.jpeg?x-expires=1692849600&x-signature=lGcqRyBJPCWRvwvvh6eKeRb9pmY%3D&from=3218412987","https://p26-sign.douyinpic.com/tos-cn-p-0015/oQP2RAbED5QCyx9HAkg8IjeDdnS3AkKenHAWBb~noop.jpeg?x-expires=1692849600&x-signature=SGmBod5oIEmzBnhZ3%2BEYooox25I%3D&from=3218412987","https://p9-sign.douyinpic.com/tos-cn-p-0015/oQP2RAbED5QCyx9HAkg8IjeDdnS3AkKenHAWBb~noop.jpeg?x-expires=1692849600&x-signature=TAhmXWWt%2F9E%2B56%2BiRkcQxC7ICuw%3D&from=3218412987"]},"word_type":1,"sentence_id":"1370673","drift_info":null,"can_extend_detail":false,"sentence_tag":5000},{"group_id":"7268114097999598904","event_time":1692760306,"word_type":1,"sentence_id":"1370819","view_count":20472119,"hotlist_param":"{\"version\":1}","article_detail_count":4,"emo_label":0,"word_cover":{"uri":"tos-cn-p-0015/osjPIVjgEAAeCerBmHehVYbeRAcNtQfeOCIZwx","url_list":["https://p3-sign.douyinpic.com/tos-cn-p-0015/osjPIVjgEAAeCerBmHehVYbeRAcNtQfeOCIZwx~noop.jpeg?x-expires=1692849600&x-signature=jqguXl9WVwdkJX1g6bH9Q3O4AJg%3D&from=3218412987","https://p9-sign.douyinpic.com/tos-cn-p-0015/osjPIVjgEAAeCerBmHehVYbeRAcNtQfeOCIZwx~noop.jpeg?x-expires=1692849600&x-signature=hPEBRoaGG4%2Bmjag%2FDLCSOWcjRzc%3D&from=3218412987","https://p26-sign.douyinpic.com/tos-cn-p-0015/osjPIVjgEAAeCerBmHehVYbeRAcNtQfeOCIZwx~noop.jpeg?x-expires=1692849600&x-signature=vkvE3xfwaPbJ1BVPotIDDYMQLSY%3D&from=3218412987"]},"position":35,"drift_info":null,"word_sub_board":null,"label":0,"can_extend_detail":false,"video_count":13,"related_words":null,"aweme_infos":null,"sentence_tag":2011,"discuss_video_count":1,"word":"李玟经纪公司回应录音事件","hot_value":8175177},{"position":36,"group_id":"7269771629584504099","can_extend_detail":false,"drift_info":null,"view_count":17810379,"aweme_infos":null,"discuss_video_count":1,"word_sub_board":null,"word":"揭秘孤注一掷扔猫戏","word_cover":{"uri":"tos-cn-p-0015/9d7e2af60bb14b5e80bceed1632427b0_1692722310","url_list":["https://p11-sign.douyinpic.com/tos-cn-p-0015/9d7e2af60bb14b5e80bceed1632427b0_1692722310~noop.jpeg?x-expires=1692849600&x-signature=B%2BmnuXtoZTRdlQg60SLTymkZqx0%3D&from=3218412987","https://p26-sign.douyinpic.com/tos-cn-p-0015/9d7e2af60bb14b5e80bceed1632427b0_1692722310~noop.jpeg?x-expires=1692849600&x-signature=202tr6STOykczVFWNK9TMyI5btk%3D&from=3218412987","https://p3-sign.douyinpic.com/tos-cn-p-0015/9d7e2af60bb14b5e80bceed1632427b0_1692722310~noop.jpeg?x-expires=1692849600&x-signature=dUKnsWJdp42y%2BvoB%2BmlrE6x0F7I%3D&from=3218412987"]},"video_count":3,"word_type":1,"sentence_id":"1371039","event_time":1692769777,"sentence_tag":2001,"label":8,"hot_value":8172680,"related_words":null,"hotlist_param":"{\"version\":1}","article_detail_count":0},{"hot_value":8165757,"group_id":"7268853691384501515","event_time":1692748937,"sentence_tag":4003,"article_detail_count":2,"related_words":null,"label":0,"word_cover":{"uri":"tos-cn-p-0004/90aae4ea0322426bbbf1cd39f7f56ef8_1692756737","url_list":["https://p3-sign.douyinpic.com/tos-cn-p-0004/90aae4ea0322426bbbf1cd39f7f56ef8_1692756737~noop.jpeg?x-expires=1692849600&x-signature=dh%2B15m%2Bb%2BHPumh1DViNyG7zFZ48%3D&from=3218412987","https://p26-sign.douyinpic.com/tos-cn-p-0004/90aae4ea0322426bbbf1cd39f7f56ef8_1692756737~noop.jpeg?x-expires=1692849600&x-signature=DU0jcOfhtdns8Job7d2TIxYiCZ4%3D&from=3218412987","https://p6-sign.douyinpic.com/tos-cn-p-0004/90aae4ea0322426bbbf1cd39f7f56ef8_1692756737~noop.jpeg?x-expires=1692849600&x-signature=j2GeeQBzgz88%2Ft4e%2B5ePTronVIE%3D&from=3218412987"]},"position":37,"word_type":1,"sentence_id":"1370498","can_extend_detail":false,"view_count":18307525,"drift_info":null,"word_sub_board":null,"word":"缅北更新电诈2.0版","video_count":9,"hotlist_param":"{\"version\":1}","aweme_infos":null,"discuss_video_count":1},{"group_id":"7267929324782343480","event_time":1692780167,"discuss_video_count":1,"word_sub_board":null,"sentence_tag":3001,"word_cover":{"uri":"tos-cn-p-0015/52a79a8805bf40a2b9431277e5fa92ef_1692707843","url_list":["https://p26-sign.douyinpic.com/tos-cn-p-0015/52a79a8805bf40a2b9431277e5fa92ef_1692707843~noop.jpeg?x-expires=1692849600&x-signature=E%2FDWZ7Sri5txshDoTP7tH1vYacI%3D&from=3218412987","https://p3-sign.douyinpic.com/tos-cn-p-0015/52a79a8805bf40a2b9431277e5fa92ef_1692707843~noop.jpeg?x-expires=1692849600&x-signature=7dME2xPxBHLa7gu%2Bg0dtdvL%2FpuE%3D&from=3218412987","https://p9-sign.douyinpic.com/tos-cn-p-0015/52a79a8805bf40a2b9431277e5fa92ef_1692707843~noop.jpeg?x-expires=1692849600&x-signature=coxx7dOCygybEKeaoE6BYmmGsik%3D&from=3218412987"]},"position":38,"can_extend_detail":false,"sentence_id":"1371338","drift_info":null,"article_detail_count":0,"word":"台胞证签发机关变了","label":0,"hot_value":8139646,"related_words":null,"aweme_infos":null,"video_count":1,"word_type":1,"view_count":16457484,"hotlist_param":"{\"version\":1}"},{"word_sub_board":null,"hot_value":8130476,"discuss_video_count":1,"group_id":"7268293053550253349","related_words":null,"aweme_infos":null,"sentence_tag":20002,"article_detail_count":0,"label":3,"position":39,"sentence_id":"1371801","event_time":1692798693,"view_count":15489944,"hotlist_param":"{\"version\":1}","video_count":1,"can_extend_detail":false,"word_type":1,"drift_info":null,"word":"车里只有马立奥懂大喜大悲","word_cover":{"uri":"tos-cn-p-0015/ooNS9J6fbACqBdnRBEVlJSQA2e7PfybkgaDIB6","url_list":["https://p26-sign.douyinpic.com/tos-cn-p-0015/ooNS9J6fbACqBdnRBEVlJSQA2e7PfybkgaDIB6~noop.jpeg?x-expires=1692849600&x-signature=P5dyt0iY%2FSNrQUX5%2BhK2BqGH960%3D&from=3218412987","https://p3-sign.douyinpic.com/tos-cn-p-0015/ooNS9J6fbACqBdnRBEVlJSQA2e7PfybkgaDIB6~noop.jpeg?x-expires=1692849600&x-signature=qjcUgSQWbyRtzQ075iTDeajj960%3D&from=3218412987","https://p9-sign.douyinpic.com/tos-cn-p-0015/ooNS9J6fbACqBdnRBEVlJSQA2e7PfybkgaDIB6~noop.jpeg?x-expires=1692849600&x-signature=A%2FwodR8yI06%2FYl5liXmpvUNf6GI%3D&from=3218412987"]}},{"hot_value":8084149,"video_count":1,"can_extend_detail":false,"word_type":1,"event_time":1692795240,"related_words":null,"aweme_infos":null,"sentence_tag":20001,"position":40,"sentence_id":"1371746","discuss_video_count":1,"word_sub_board":null,"article_detail_count":1,"word":"日本核污染水是怎么产生的","label":0,"word_cover":{"uri":"tos-cn-p-0015/owBSAA55bezAJAgBEkDnNHb6IA6tgBRfADmFc9","url_list":["https://p9-sign.douyinpic.com/tos-cn-p-0015/owBSAA55bezAJAgBEkDnNHb6IA6tgBRfADmFc9~noop.jpeg?x-expires=1692849600&x-signature=wwDLKQ0Xlg%2BmCe3teVhGlqh3SJs%3D&from=3218412987","https://p3-sign.douyinpic.com/tos-cn-p-0015/owBSAA55bezAJAgBEkDnNHb6IA6tgBRfADmFc9~noop.jpeg?x-expires=1692849600&x-signature=M20tqYhXynPrkTiOhf4BGvhbBI8%3D&from=3218412987","https://p26-sign.douyinpic.com/tos-cn-p-0015/owBSAA55bezAJAgBEkDnNHb6IA6tgBRfADmFc9~noop.jpeg?x-expires=1692849600&x-signature=C4BMBd3%2F%2B4dn5wH0oF6W3hHpo8I%3D&from=3218412987"]},"group_id":"6883380263964775691","view_count":14054648,"drift_info":null,"hotlist_param":"{\"version\":1}"},{"sentence_tag":20002,"word":"这催婚也太硬核了","event_time":1692779793,"related_words":null,"article_detail_count":0,"group_id":"7269847315836900643","word_type":1,"word_sub_board":null,"hotlist_param":"{\"version\":1}","discuss_video_count":1,"word_cover":{"uri":"tos-cn-p-0015/489ec0e4f8b346788ebfe3dec0a01fdd_1692777792","url_list":["https://p9-sign.douyinpic.com/tos-cn-p-0015/489ec0e4f8b346788ebfe3dec0a01fdd_1692777792~noop.jpeg?x-expires=1692849600&x-signature=%2Bnxi6oD2lMYZdnHRe9ySdKL4Jcw%3D&from=3218412987","https://p3-sign.douyinpic.com/tos-cn-p-0015/489ec0e4f8b346788ebfe3dec0a01fdd_1692777792~noop.jpeg?x-expires=1692849600&x-signature=NSlK21vrdigSAW8NtNo%2FTLQc%2B6I%3D&from=3218412987","https://p6-sign.douyinpic.com/tos-cn-p-0015/489ec0e4f8b346788ebfe3dec0a01fdd_1692777792~noop.jpeg?x-expires=1692849600&x-signature=516UXvMxHxZyJdBu7itq58ZJFX8%3D&from=3218412987"]},"view_count":11019291,"drift_info":null,"video_count":6,"can_extend_detail":false,"sentence_id":"1371314","aweme_infos":null,"label":0,"hot_value":8023929,"position":41},{"aweme_infos":null,"discuss_video_count":1,"position":42,"sentence_id":"1370649","detail_info":{"detail_type":0,"detail_desc":"事件详情"},"hotlist_param":"{\"version\":1}","video_count":4,"drift_info":null,"article_detail_count":1,"emo_label":0,"can_extend_detail":true,"word_type":1,"related_words":null,"sentence_tag":2011,"word":"涂磊为李玟发声","hot_value":7932203,"word_cover":{"uri":"tos-cn-p-0015/oARleoUFyEDNAuAMCBcfK7PhIFzB4OAuzgtjJj","url_list":["https://p6-sign.douyinpic.com/tos-cn-p-0015/oARleoUFyEDNAuAMCBcfK7PhIFzB4OAuzgtjJj~noop.jpeg?x-expires=1692849600&x-signature=MDxR9VPFDVYOhWcK%2FSMKueKG5UM%3D&from=3218412987","https://p3-sign.douyinpic.com/tos-cn-p-0015/oARleoUFyEDNAuAMCBcfK7PhIFzB4OAuzgtjJj~noop.jpeg?x-expires=1692849600&x-signature=cvqbS6psGuzCVQQSgumm0qA9KVA%3D&from=3218412987","https://p26-sign.douyinpic.com/tos-cn-p-0015/oARleoUFyEDNAuAMCBcfK7PhIFzB4OAuzgtjJj~noop.jpeg?x-expires=1692849600&x-signature=wF9hqxsTKZKuVK0IbqBIOL7ppy0%3D&from=3218412987"]},"group_id":"7252574340189246772","label":3,"event_time":1692754226,"view_count":10193329,"word_sub_board":null},{"video_count":3,"hotlist_param":"{\"version\":1}","aweme_infos":null,"label":0,"word_cover":{"url_list":["https://p26-sign.douyinpic.com/tos-cn-p-0015/2a197222dd324c04bd84e2064e5b4913_1692755594~noop.jpeg?x-expires=1692849600&x-signature=E4FZlzauHNYOQuWgz1DvxVtcFgs%3D&from=3218412987","https://p3-sign.douyinpic.com/tos-cn-p-0015/2a197222dd324c04bd84e2064e5b4913_1692755594~noop.jpeg?x-expires=1692849600&x-signature=MJ4mSkm4kSd07plQ%2BButwqA%2B1pA%3D&from=3218412987","https://p6-sign.douyinpic.com/tos-cn-p-0015/2a197222dd324c04bd84e2064e5b4913_1692755594~noop.jpeg?x-expires=1692849600&x-signature=xQ1L9Z6WLWZ3p2wmyIWR%2Btp1r%2Bc%3D&from=3218412987"],"uri":"tos-cn-p-0015/2a197222dd324c04bd84e2064e5b4913_1692755594"},"word_type":1,"event_time":1692755734,"related_words":null,"word_sub_board":null,"word":"越媒：越南副总理黎文成去世","can_extend_detail":false,"sentence_id":"1370699","sentence_tag":3002,"discuss_video_count":1,"hot_value":7896605,"position":43,"group_id":"7268898104191522084","view_count":9412156,"drift_info":null,"article_detail_count":5},{"related_words":null,"sentence_tag":3001,"discuss_video_count":1,"word":"广东省委第二巡视组组长主动投案","position":44,"group_id":"7268893074329163044","can_extend_detail":false,"sentence_id":"1370609","label":3,"hot_value":7822142,"video_count":3,"view_count":7271437,"article_detail_count":1,"word_type":1,"drift_info":null,"hotlist_param":"{\"version\":1}","aweme_infos":null,"word_cover":{"uri":"tos-cn-p-0015/og9LRAh2AqfQeBGkaVC8DhB5IB6blgLlqgnWAt","url_list":["https://p3-sign.douyinpic.com/tos-cn-p-0015/og9LRAh2AqfQeBGkaVC8DhB5IB6blgLlqgnWAt~noop.jpeg?x-expires=1692849600&x-signature=d0y%2BYEHyd6u1%2FH0I25lbgmIQQRA%3D&from=3218412987","https://p9-sign.douyinpic.com/tos-cn-p-0015/og9LRAh2AqfQeBGkaVC8DhB5IB6blgLlqgnWAt~noop.jpeg?x-expires=1692849600&x-signature=pxZr3pEiSL4HJ%2BBY1eyNP3BivMw%3D&from=3218412987","https://p26-sign.douyinpic.com/tos-cn-p-0015/og9LRAh2AqfQeBGkaVC8DhB5IB6blgLlqgnWAt~noop.jpeg?x-expires=1692849600&x-signature=J3SGHTE9omtKmJgieEScv2EbeZ8%3D&from=3218412987"]},"event_time":1692752754,"word_sub_board":null},{"word_cover":{"uri":"tos-cn-p-0015/oUDEAPh6hfANPcBgIeuzCcppwwEdlJymJAONBs","url_list":["https://p3-sign.douyinpic.com/tos-cn-p-0015/oUDEAPh6hfANPcBgIeuzCcppwwEdlJymJAONBs~noop.jpeg?x-expires=1692849600&x-signature=kcVlOva0cvOqRs3%2BPl%2BmROj9fiA%3D&from=3218412987","https://p6-sign.douyinpic.com/tos-cn-p-0015/oUDEAPh6hfANPcBgIeuzCcppwwEdlJymJAONBs~noop.jpeg?x-expires=1692849600&x-signature=CJyAIwmJn8IWWp3FcqDHVms%2B140%3D&from=3218412987","https://p26-sign.douyinpic.com/tos-cn-p-0015/oUDEAPh6hfANPcBgIeuzCcppwwEdlJymJAONBs~noop.jpeg?x-expires=1692849600&x-signature=wM%2BlhzS%2FKYoI60vvBSvPRtnwkzk%3D&from=3218412987"]},"can_extend_detail":false,"word_type":1,"aweme_infos":null,"sentence_tag":5000,"group_id":"7269160461579359507","sentence_id":"1371863","event_time":1692804222,"drift_info":null,"label":5,"hot_value":7770485,"hotlist_param":"{\"version\":1}","discuss_video_count":1,"word_sub_board":null,"word":"赖益烨单挑戈登圆梦","position":45,"video_count":1,"related_words":null,"view_count":7316003,"article_detail_count":0},{"label":8,"word_cover":{"uri":"tos-cn-p-0015/fb7d3b2ae3ca4a839fba02592aa32a6f_1692723521","url_list":["https://p26-sign.douyinpic.com/tos-cn-p-0015/fb7d3b2ae3ca4a839fba02592aa32a6f_1692723521~noop.jpeg?x-expires=1692849600&x-signature=qIjvH%2Bnw%2B%2BYZPRLdasL0wSMCgg0%3D&from=3218412987","https://p3-sign.douyinpic.com/tos-cn-p-0015/fb7d3b2ae3ca4a839fba02592aa32a6f_1692723521~noop.jpeg?x-expires=1692849600&x-signature=b1hXgIHabYVTZ1uxFe%2BZjO4%2FJr0%3D&from=3218412987","https://p6-sign.douyinpic.com/tos-cn-p-0015/fb7d3b2ae3ca4a839fba02592aa32a6f_1692723521~noop.jpeg?x-expires=1692849600&x-signature=frAxKEuMnwJsXPHju5Ab5ngXkas%3D&from=3218412987"]},"word_type":1,"sentence_id":"1370883","event_time":1692763070,"discuss_video_count":1,"article_detail_count":0,"word":"杨紫檀健次嘿嘿式对戏","word_sub_board":null,"view_count":5114996,"can_extend_detail":false,"related_words":null,"drift_info":null,"sentence_tag":2002,"video_count":7,"position":46,"group_id":"7270241038232720652","hotlist_param":"{\"version\":1}","aweme_infos":null,"hot_value":7690219},{"related_words":null,"aweme_infos":null,"view_count":3543461,"discuss_video_count":1,"article_detail_count":5,"label":3,"hot_value":7615342,"sentence_id":"1370985","can_extend_detail":false,"hotlist_param":"{\"version\":1}","sentence_tag":4004,"word_sub_board":null,"word":"广东外卖单点不送可举报","video_count":3,"group_id":"7267573750676755770","event_time":1692768342,"drift_info":null,"word_cover":{"uri":"tos-cn-p-0015/ogLHPgLCILJAINMerQHRC5yB7B3PkAZGJQ2fe9","url_list":["https://p3-sign.douyinpic.com/tos-cn-p-0015/ogLHPgLCILJAINMerQHRC5yB7B3PkAZGJQ2fe9~noop.jpeg?x-expires=1692849600&x-signature=cTVLLgxf0LY2cj1QV6M6Yd64Lsc%3D&from=3218412987","https://p26-sign.douyinpic.com/tos-cn-p-0015/ogLHPgLCILJAINMerQHRC5yB7B3PkAZGJQ2fe9~noop.jpeg?x-expires=1692849600&x-signature=WuU%2Fdn%2Fdo6KDTeRJNOYUwi0J4uA%3D&from=3218412987","https://p9-sign.douyinpic.com/tos-cn-p-0015/ogLHPgLCILJAINMerQHRC5yB7B3PkAZGJQ2fe9~noop.jpeg?x-expires=1692849600&x-signature=68NomVhOzqKaRwlo6o54DEMkHQw%3D&from=3218412987"]},"position":47,"word_type":1},{"can_extend_detail":true,"word_type":1,"sentence_id":"1371240","related_words":null,"drift_info":null,"word":"乌尔善说封神2明年暑期上映","position":48,"group_id":"7269043057953396022","display_style":0,"discuss_video_count":1,"word_cover":{"uri":"tos-cn-p-0015/f217593441a749ef8c43943189ddd06a","url_list":["https://p26-sign.douyinpic.com/tos-cn-p-0015/f217593441a749ef8c43943189ddd06a~noop.jpeg?x-expires=1692849600&x-signature=ABZ9PA4MS84%2FBwdl5JxzyY4LrOo%3D&from=3218412987","https://p3-sign.douyinpic.com/tos-cn-p-0015/f217593441a749ef8c43943189ddd06a~noop.jpeg?x-expires=1692849600&x-signature=Kt32z7WuUF0NOjzFvnzevv4urD8%3D&from=3218412987","https://p6-sign.douyinpic.com/tos-cn-p-0015/f217593441a749ef8c43943189ddd06a~noop.jpeg?x-expires=1692849600&x-signature=EL890wRc2CCxndq8k1yjALOamUo%3D&from=3218412987"]},"view_count":2802002,"detail_info":{"detail_type":1,"detail_desc":"事件详情"},"aweme_infos":null,"label":3,"video_count":3,"event_time":1692777624,"word_sub_board":null,"article_detail_count":2,"hot_value":7583910,"hotlist_param":"{\"version\":1}","sentence_tag":2001},{"event_time":1692759372,"hotlist_param":"{\"version\":1}","aweme_infos":null,"hot_value":7471549,"video_count":4,"can_extend_detail":false,"sentence_id":"1370785","sentence_tag":2002,"word_sub_board":null,"word":"长相思玱玹继承西炎王之位","word_cover":{"uri":"tos-cn-p-0015/353895c9284a4cc68c0b7a4081c3f041_1692637074","url_list":["https://p26-sign.douyinpic.com/tos-cn-p-0015/353895c9284a4cc68c0b7a4081c3f041_1692637074~noop.jpeg?x-expires=1692849600&x-signature=8NqB1mV8988XxI3eJoyRAelW0nU%3D&from=3218412987","https://p11-sign.douyinpic.com/tos-cn-p-0015/353895c9284a4cc68c0b7a4081c3f041_1692637074~noop.jpeg?x-expires=1692849600&x-signature=E6I%2B7epqV96XF2DzgA8Vl2zkVgk%3D&from=3218412987","https://p6-sign.douyinpic.com/tos-cn-p-0015/353895c9284a4cc68c0b7a4081c3f041_1692637074~noop.jpeg?x-expires=1692849600&x-signature=97xctsUt1IMevF97F3yc%2BW4N890%3D&from=3218412987"]},"group_id":"7269677770908144933","drift_info":null,"position":49,"view_count":945896,"discuss_video_count":1,"article_detail_count":1,"label":0,"word_type":1,"related_words":null},{"article_detail_count":0,"position":50,"group_id":"7268215945775830309","can_extend_detail":false,"related_words":null,"discuss_video_count":1,"word":"魏大勋沈腾只差四斤","hot_value":7453854,"view_count":6874530,"sentence_tag":2003,"label":0,"word_type":1,"sentence_id":"1371485","event_time":1692784977,"word_sub_board":null,"word_cover":{"uri":"tos-cn-p-0015/o8kL9k4E53ZDAC0bAAQwoUSbizfgOeInBFCBYY","url_list":["https://p3-sign.douyinpic.com/tos-cn-p-0015/o8kL9k4E53ZDAC0bAAQwoUSbizfgOeInBFCBYY~noop.jpeg?x-expires=1692849600&x-signature=5amEB%2Fo%2FX8%2BSXzH7cqhw3HC%2Bxwk%3D&from=3218412987","https://p26-sign.douyinpic.com/tos-cn-p-0015/o8kL9k4E53ZDAC0bAAQwoUSbizfgOeInBFCBYY~noop.jpeg?x-expires=1692849600&x-signature=8mLTrvRBWzNm6acXoc4xCwI1R48%3D&from=3218412987","https://p9-sign.douyinpic.com/tos-cn-p-0015/o8kL9k4E53ZDAC0bAAQwoUSbizfgOeInBFCBYY~noop.jpeg?x-expires=1692849600&x-signature=DdM6Yw%2B%2BNCKHLjWW5L%2FTWX2c5DI%3D&from=3218412987"]},"video_count":1,"drift_info":null,"hotlist_param":"{\"version\":1}","aweme_infos":null}],"active_time":"2023-08-24 06:16:46","share_info":{"share_link_desc":"我在看抖音热榜，发现最火的内容，赶快来看！戳这里>>","share_url":"https://www.iesdouyin.com/share/billboard/?id=0","share_title":"我在看抖音热榜，发现最火的内容，赶快来看！"},"trending_list":[{"word_cover":{"uri":"tos-cn-p-0015/oMAAE2HLSgkQbBQ2EPncZIPfD5m9D2egLMnAmc","url_list":["https://p3-sign.douyinpic.com/tos-cn-p-0015/oMAAE2HLSgkQbBQ2EPncZIPfD5m9D2egLMnAmc~noop.jpeg?x-expires=1692849600&x-signature=4jketxhwlCGgFx0S63FT1Nz8cOw%3D&from=3218412987","https://p9-sign.douyinpic.com/tos-cn-p-0015/oMAAE2HLSgkQbBQ2EPncZIPfD5m9D2egLMnAmc~noop.jpeg?x-expires=1692849600&x-signature=tTE0SGMojmBzzi6TAAa4cHpHgI0%3D&from=3218412987","https://p6-sign.douyinpic.com/tos-cn-p-0015/oMAAE2HLSgkQbBQ2EPncZIPfD5m9D2egLMnAmc~noop.jpeg?x-expires=1692849600&x-signature=R5thE72x2N9K7g9aJBNRDGZlMFc%3D&from=3218412987"]},"event_time":1692782345,"sentence_tag":22001,"word_sub_board":null,"word":"台风苏拉对我国的影响","hotlist_param":"{\"version\":1}","aweme_infos":null,"discuss_video_count":1,"sentence_id":"1371425","related_words":null,"article_detail_count":0,"label":0,"video_count":3,"group_id":"7269017477831906599","word_type":3,"hot_value":0,"drift_info":null},{"word_cover":{"uri":"tos-cn-p-0015/d3f7b1a14f3e460f9bd069d73c4022ae_1692800682","url_list":["https://p9-sign.douyinpic.com/tos-cn-p-0015/d3f7b1a14f3e460f9bd069d73c4022ae_1692800682~noop.jpeg?x-expires=1692849600&x-signature=6mLpqpj3hs3bE5qG3ZDFrnnKg9w%3D&from=3218412987","https://p26-sign.douyinpic.com/tos-cn-p-0015/d3f7b1a14f3e460f9bd069d73c4022ae_1692800682~noop.jpeg?x-expires=1692849600&x-signature=3ZWRQF7wOqthHZcjOCWiwvbtukI%3D&from=3218412987","https://p11-sign.douyinpic.com/tos-cn-p-0015/d3f7b1a14f3e460f9bd069d73c4022ae_1692800682~noop.jpeg?x-expires=1692849600&x-signature=kPq9bly9I4N7bZHa5rkx30Hb43M%3D&from=3218412987"]},"word_sub_board":null,"hot_value":0,"group_id":"7269168266132084009","event_time":1692804066,"discuss_video_count":1,"aweme_infos":null,"sentence_tag":5000,"word":"黄文祺单挑绝杀戈登","label":5,"video_count":2,"related_words":null,"article_detail_count":0,"word_type":3,"sentence_id":"1371858","drift_info":null,"hotlist_param":"{\"version\":1}"},{"discuss_video_count":0,"word_sub_board":null,"video_count":11,"event_time":1692773578,"hotlist_param":"{\"version\":1}","sentence_id":"1371160","label":0,"word_cover":{"uri":"tos-cn-p-0015/oogkeykQcXxhA3WLAAIkEE4tm9XgkfEzB6NBjm","url_list":["https://p3-sign.douyinpic.com/tos-cn-p-0015/oogkeykQcXxhA3WLAAIkEE4tm9XgkfEzB6NBjm~noop.jpeg?x-expires=1692849600&x-signature=sVdsYKQ5XV0eqXZjNz%2FdtrKnx2k%3D&from=3218412987","https://p6-sign.douyinpic.com/tos-cn-p-0015/oogkeykQcXxhA3WLAAIkEE4tm9XgkfEzB6NBjm~noop.jpeg?x-expires=1692849600&x-signature=48hm28c6eTdZruTCyDo3p1L6un8%3D&from=3218412987","https://p11-sign.douyinpic.com/tos-cn-p-0015/oogkeykQcXxhA3WLAAIkEE4tm9XgkfEzB6NBjm~noop.jpeg?x-expires=1692849600&x-signature=HQ2jxNXc15BjACDHIzNpP6l1sy0%3D&from=3218412987"]},"room_count":0,"drift_info":null,"aweme_infos":null,"sentence_tag":20005,"hot_value":0,"group_id":"7268979421561148683","word_type":3,"article_detail_count":4,"word":"海鲜和日料还能吃吗","related_words":null,"display_style":0},{"sentence_tag":22002,"discuss_video_count":1,"label":0,"group_id":"7269044041202242827","word_type":3,"sentence_id":"1371597","drift_info":null,"aweme_infos":null,"word":"山东吉林等地有震感","word_cover":{"uri":"tos-cn-p-0015/o8fUYBGnJC5CW7weD58eGAEmBBGlbyBAY7IV71","url_list":["https://p3-sign.douyinpic.com/tos-cn-p-0015/o8fUYBGnJC5CW7weD58eGAEmBBGlbyBAY7IV71~noop.jpeg?x-expires=1692849600&x-signature=iKv0alFpdL7rTGojlBNcKzZPKKM%3D&from=3218412987","https://p26-sign.douyinpic.com/tos-cn-p-0015/o8fUYBGnJC5CW7weD58eGAEmBBGlbyBAY7IV71~noop.jpeg?x-expires=1692849600&x-signature=d80Qc1Yg7ZKcq0tK2mtTGssAbig%3D&from=3218412987","https://p6-sign.douyinpic.com/tos-cn-p-0015/o8fUYBGnJC5CW7weD58eGAEmBBGlbyBAY7IV71~noop.jpeg?x-expires=1692849600&x-signature=wEk99cjup22DsdxvLPaBA8BDAiE%3D&from=3218412987"]},"event_time":1692786833,"related_words":null,"hotlist_param":"{\"version\":1}","word_sub_board":null,"hot_value":0,"video_count":1},{"label":0,"video_count":7,"sentence_id":"1370800","drift_info":null,"word_sub_board":null,"word_type":3,"event_time":1692759632,"hotlist_param":"{\"version\":1}","sentence_tag":2001,"word_cover":{"uri":"tos-cn-p-0015/36f540a7e2b14a939e536febc6eeea10_1692753805","url_list":["https://p26-sign.douyinpic.com/tos-cn-p-0015/36f540a7e2b14a939e536febc6eeea10_1692753805~noop.jpeg?x-expires=1692849600&x-signature=yoGV%2BEyL5%2BaCW2%2F0sVLcgnkCi2c%3D&from=3218412987","https://p9-sign.douyinpic.com/tos-cn-p-0015/36f540a7e2b14a939e536febc6eeea10_1692753805~noop.jpeg?x-expires=1692849600&x-signature=RVpXcX4CX8%2FhSQ7dD8Emv5FNnmI%3D&from=3218412987","https://p3-sign.douyinpic.com/tos-cn-p-0015/36f540a7e2b14a939e536febc6eeea10_1692753805~noop.jpeg?x-expires=1692849600&x-signature=qJ3lok37VNvyI3CX0IOpFe9MskU%3D&from=3218412987"]},"aweme_infos":null,"discuss_video_count":0,"article_detail_count":3,"word":"燃冬搞笑影评","hot_value":0,"group_id":"7268122640652522789","related_words":null}],"trending_desc":"实时上升热点","recommend_list":null},"ad_search_list":null,"banner_dark":{"uri":"32e5200049fac86168117","url_list":["https://p6-sign.douyinpic.com/obj/32e5200049fac86168117?x-expires=1692849600&x-signature=RRCO9M5%2F5%2FHuvF7jmKgToZUl9CA%3D&from=65706370","https://p26-sign.douyinpic.com/obj/32e5200049fac86168117?x-expires=1692849600&x-signature=rdVuwEpcnXT%2BmQNy1UVYdJXIxkk%3D&from=65706370","https://p3-sign.douyinpic.com/obj/32e5200049fac86168117?x-expires=1692849600&x-signature=Js15EjuqCUBLNh4IiQq%2BRCJ64zk%3D&from=65706370"]},"banner_light":{"uri":"321f4000f703369c24604","url_list":["https://p11-sign.douyinpic.com/obj/321f4000f703369c24604?x-expires=1692849600&x-signature=phKi13eFyuf32JNVyEX49ueFDLA%3D&from=65706370","https://p6-sign.douyinpic.com/obj/321f4000f703369c24604?x-expires=1692849600&x-signature=qBap6WefUttmytpq0i%2Fp6ZrJnNY%3D&from=65706370","https://p3-sign.douyinpic.com/obj/321f4000f703369c24604?x-expires=1692849600&x-signature=4bNMy00mZBFxyX4Fg6PHyTkg0Z4%3D&from=65706370"]},"board_tabs":null,"extra":{"now":1692829056000,"fatal_item_ids":[],"logid":"2023082406173695E8BFC8F09A3C2A7DCD"},"log_pb":{"impr_id":"2023082406173695E8BFC8F09A3C2A7DCD"},"status_code":0}
